[{"id":"88456","codigo_postal_asentamiento":"67940","nombre_asentamiento":"Brownsville","tipo_asentamiento":"Colonia","nombre_municipio":"Aramberri","nombre_estado":"Nuevo Le\u00f3n","nombre_ciudad":"","codigo_postal_oficina":"67901","clave_estado":"19","codigo_postal_oficina_":"67901","c_cp_vacio":"","clave_tipo_asentamiento":"09","clave_municipio":"7","identificador_asentamiento":"5395","zona_asentamiento":"Urbano","clave_interna_cp_ciudad":""},{"id":"88457","codigo_postal_asentamiento":"67940","nombre_asentamiento":"El Calichal","tipo_asentamiento":"Colonia","nombre_municipio":"Aramberri","nombre_estado":"Nuevo Le\u00f3n","nombre_ciudad":"","codigo_postal_oficina":"67901","clave_estado":"19","codigo_postal_oficina_":"67901","c_cp_vacio":"","clave_tipo_asentamiento":"09","clave_municipio":"7","identificador_asentamiento":"5396","zona_asentamiento":"Urbano","clave_interna_cp_ciudad":""},{"id":"88458","codigo_postal_asentamiento":"67940","nombre_asentamiento":"La Tijera","tipo_asentamiento":"Colonia","nombre_municipio":"Aramberri","nombre_estado":"Nuevo Le\u00f3n","nombre_ciudad":"","codigo_postal_oficina":"67901","clave_estado":"19","codigo_postal_oficina_":"67901","c_cp_vacio":"","clave_tipo_asentamiento":"09","clave_municipio":"7","identificador_asentamiento":"5398","zona_asentamiento":"Urbano","clave_interna_cp_ciudad":""},{"id":"88459","codigo_postal_asentamiento":"67940","nombre_asentamiento":"Aramberri Centro","tipo_asentamiento":"Colonia","nombre_municipio":"Aramberri","nombre_estado":"Nuevo Le\u00f3n","nombre_ciudad":"","codigo_postal_oficina":"67901","clave_estado":"19","codigo_postal_oficina_":"67901","c_cp_vacio":"","clave_tipo_asentamiento":"09","clave_municipio":"7","identificador_asentamiento":"2394","zona_asentamiento":"Rural","clave_interna_cp_ciudad":""},{"id":"88460","codigo_postal_asentamiento":"67940","nombre_asentamiento":"Emiliano Zapata","tipo_asentamiento":"Colonia","nombre_municipio":"Aramberri","nombre_estado":"Nuevo Le\u00f3n","nombre_ciudad":"","codigo_postal_oficina":"67901","clave_estado":"19","codigo_postal_oficina_":"67901","c_cp_vacio":"","clave_tipo_asentamiento":"09","clave_municipio":"7","identificador_asentamiento":"5397","zona_asentamiento":"Urbano","clave_interna_cp_ciudad":""},{"id":"88461","codigo_postal_asentamiento":"67940","nombre_asentamiento":"Secci\u00f3n Norte","tipo_asentamiento":"Colonia","nombre_municipio":"Aramberri","nombre_estado":"Nuevo Le\u00f3n","nombre_ciudad":"","codigo_postal_oficina":"67901","clave_estado":"19","codigo_postal_oficina_":"67901","c_cp_vacio":"","clave_tipo_asentamiento":"09","clave_municipio":"7","identificador_asentamiento":"5399","zona_asentamiento":"Urbano","clave_interna_cp_ciudad":""},{"id":"88462","codigo_postal_asentamiento":"67940","nombre_asentamiento":"Secci\u00f3n Sur","tipo_asentamiento":"Colonia","nombre_municipio":"Aramberri","nombre_estado":"Nuevo Le\u00f3n","nombre_ciudad":"","codigo_postal_oficina":"67901","clave_estado":"19","codigo_postal_oficina_":"67901","c_cp_vacio":"","clave_tipo_asentamiento":"09","clave_municipio":"7","identificador_asentamiento":"5400","zona_asentamiento":"Urbano","clave_interna_cp_ciudad":""},{"id":"88463","codigo_postal_asentamiento":"67943","nombre_asentamiento":"Agua Adentro","tipo_asentamiento":"Poblado comunal","nombre_municipio":"Aramberri","nombre_estado":"Nuevo Le\u00f3n","nombre_ciudad":"","codigo_postal_oficina":"67901","clave_estado":"19","codigo_postal_oficina_":"67901","c_cp_vacio":"","clave_tipo_asentamiento":"27","clave_municipio":"7","identificador_asentamiento":"5232","zona_asentamiento":"Rural","clave_interna_cp_ciudad":""},{"id":"88464","codigo_postal_asentamiento":"67943","nombre_asentamiento":"La Pe\u00f1a","tipo_asentamiento":"Poblado comunal","nombre_municipio":"Aramberri","nombre_estado":"Nuevo Le\u00f3n","nombre_ciudad":"","codigo_postal_oficina":"67901","clave_estado":"19","codigo_postal_oficina_":"67901","c_cp_vacio":"","clave_tipo_asentamiento":"27","clave_municipio":"7","identificador_asentamiento":"5328","zona_asentamiento":"Rural","clave_interna_cp_ciudad":""},{"id":"88465","codigo_postal_asentamiento":"67943","nombre_asentamiento":"El Rosario","tipo_asentamiento":"Poblado comunal","nombre_municipio":"Aramberri","nombre_estado":"Nuevo Le\u00f3n","nombre_ciudad":"","codigo_postal_oficina":"67901","clave_estado":"19","codigo_postal_oficina_":"67901","c_cp_vacio":"","clave_tipo_asentamiento":"27","clave_municipio":"7","identificador_asentamiento":"5286","zona_asentamiento":"Rural","clave_interna_cp_ciudad":""},{"id":"88466","codigo_postal_asentamiento":"67943","nombre_asentamiento":"Fraccionamiento del R\u00edo (Fracci\u00f3n del R\u00edo)","tipo_asentamiento":"Poblado comunal","nombre_municipio":"Aramberri","nombre_estado":"Nuevo Le\u00f3n","nombre_ciudad":"","codigo_postal_oficina":"67901","clave_estado":"19","codigo_postal_oficina_":"67901","c_cp_vacio":"","clave_tipo_asentamiento":"27","clave_municipio":"7","identificador_asentamiento":"5298","zona_asentamiento":"Rural","clave_interna_cp_ciudad":""},{"id":"88467","codigo_postal_asentamiento":"67943","nombre_asentamiento":"Garza","tipo_asentamiento":"Poblado comunal","nombre_municipio":"Aramberri","nombre_estado":"Nuevo Le\u00f3n","nombre_ciudad":"","codigo_postal_oficina":"67901","clave_estado":"19","codigo_postal_oficina_":"67901","c_cp_vacio":"","clave_tipo_asentamiento":"27","clave_municipio":"7","identificador_asentamiento":"5299","zona_asentamiento":"Rural","clave_interna_cp_ciudad":""},{"id":"88468","codigo_postal_asentamiento":"67943","nombre_asentamiento":"Marmolejo","tipo_asentamiento":"Poblado comunal","nombre_municipio":"Aramberri","nombre_estado":"Nuevo Le\u00f3n","nombre_ciudad":"","codigo_postal_oficina":"67901","clave_estado":"19","codigo_postal_oficina_":"67901","c_cp_vacio":"","clave_tipo_asentamiento":"27","clave_municipio":"7","identificador_asentamiento":"5355","zona_asentamiento":"Rural","clave_interna_cp_ciudad":""},{"id":"88469","codigo_postal_asentamiento":"67943","nombre_asentamiento":"Hoyas y Antiojitos","tipo_asentamiento":"Rancher\u00eda","nombre_municipio":"Aramberri","nombre_estado":"Nuevo Le\u00f3n","nombre_ciudad":"","codigo_postal_oficina":"67901","clave_estado":"19","codigo_postal_oficina_":"67901","c_cp_vacio":"","clave_tipo_asentamiento":"29","clave_municipio":"7","identificador_asentamiento":"2403","zona_asentamiento":"Rural","clave_interna_cp_ciudad":""},{"id":"88470","codigo_postal_asentamiento":"67943","nombre_asentamiento":"Chaloa (San Mauricio)","tipo_asentamiento":"Poblado comunal","nombre_municipio":"Aramberri","nombre_estado":"Nuevo Le\u00f3n","nombre_ciudad":"","codigo_postal_oficina":"67901","clave_estado":"19","codigo_postal_oficina_":"67901","c_cp_vacio":"","clave_tipo_asentamiento":"27","clave_municipio":"7","identificador_asentamiento":"5244","zona_asentamiento":"Rural","clave_interna_cp_ciudad":""},{"id":"88471","codigo_postal_asentamiento":"67943","nombre_asentamiento":"La Paila","tipo_asentamiento":"Poblado comunal","nombre_municipio":"Aramberri","nombre_estado":"Nuevo Le\u00f3n","nombre_ciudad":"","codigo_postal_oficina":"67901","clave_estado":"19","codigo_postal_oficina_":"67901","c_cp_vacio":"","clave_tipo_asentamiento":"27","clave_municipio":"7","identificador_asentamiento":"5326","zona_asentamiento":"Rural","clave_interna_cp_ciudad":""},{"id":"88472","codigo_postal_asentamiento":"67943","nombre_asentamiento":"Las Higueritas","tipo_asentamiento":"Poblado comunal","nombre_municipio":"Aramberri","nombre_estado":"Nuevo Le\u00f3n","nombre_ciudad":"","codigo_postal_oficina":"67901","clave_estado":"19","codigo_postal_oficina_":"67901","c_cp_vacio":"","clave_tipo_asentamiento":"27","clave_municipio":"7","identificador_asentamiento":"5342","zona_asentamiento":"Rural","clave_interna_cp_ciudad":""},{"id":"88473","codigo_postal_asentamiento":"67943","nombre_asentamiento":"Las Veredas","tipo_asentamiento":"Poblado comunal","nombre_municipio":"Aramberri","nombre_estado":"Nuevo Le\u00f3n","nombre_ciudad":"","codigo_postal_oficina":"67901","clave_estado":"19","codigo_postal_oficina_":"67901","c_cp_vacio":"","clave_tipo_asentamiento":"27","clave_municipio":"7","identificador_asentamiento":"5350","zona_asentamiento":"Rural","clave_interna_cp_ciudad":""},{"id":"88474","codigo_postal_asentamiento":"67943","nombre_asentamiento":"Jes\u00fas Mar\u00eda","tipo_asentamiento":"Poblado comunal","nombre_municipio":"Aramberri","nombre_estado":"Nuevo Le\u00f3n","nombre_ciudad":"","codigo_postal_oficina":"67901","clave_estado":"19","codigo_postal_oficina_":"67901","c_cp_vacio":"","clave_tipo_asentamiento":"27","clave_municipio":"7","identificador_asentamiento":"5305","zona_asentamiento":"Rural","clave_interna_cp_ciudad":""},{"id":"88475","codigo_postal_asentamiento":"67943","nombre_asentamiento":"La Vieja","tipo_asentamiento":"Poblado comunal","nombre_municipio":"Aramberri","nombre_estado":"Nuevo Le\u00f3n","nombre_ciudad":"","codigo_postal_oficina":"67901","clave_estado":"19","codigo_postal_oficina_":"67901","c_cp_vacio":"","clave_tipo_asentamiento":"27","clave_municipio":"7","identificador_asentamiento":"5336","zona_asentamiento":"Rural","clave_interna_cp_ciudad":""},{"id":"88476","codigo_postal_asentamiento":"67943","nombre_asentamiento":"Santa Teresa","tipo_asentamiento":"Poblado comunal","nombre_municipio":"Aramberri","nombre_estado":"Nuevo Le\u00f3n","nombre_ciudad":"","codigo_postal_oficina":"67901","clave_estado":"19","codigo_postal_oficina_":"67901","c_cp_vacio":"","clave_tipo_asentamiento":"27","clave_municipio":"7","identificador_asentamiento":"5392","zona_asentamiento":"Rural","clave_interna_cp_ciudad":""},{"id":"88477","codigo_postal_asentamiento":"67943","nombre_asentamiento":"Agua Fr\u00eda","tipo_asentamiento":"Poblado comunal","nombre_municipio":"Aramberri","nombre_estado":"Nuevo Le\u00f3n","nombre_ciudad":"","codigo_postal_oficina":"67901","clave_estado":"19","codigo_postal_oficina_":"67901","c_cp_vacio":"","clave_tipo_asentamiento":"27","clave_municipio":"7","identificador_asentamiento":"5236","zona_asentamiento":"Rural","clave_interna_cp_ciudad":""},{"id":"88478","codigo_postal_asentamiento":"67943","nombre_asentamiento":"El Nogalar (La Pita)","tipo_asentamiento":"Poblado comunal","nombre_municipio":"Aramberri","nombre_estado":"Nuevo Le\u00f3n","nombre_ciudad":"","codigo_postal_oficina":"67901","clave_estado":"19","codigo_postal_oficina_":"67901","c_cp_vacio":"","clave_tipo_asentamiento":"27","clave_municipio":"7","identificador_asentamiento":"5270","zona_asentamiento":"Rural","clave_interna_cp_ciudad":""},{"id":"88479","codigo_postal_asentamiento":"67943","nombre_asentamiento":"Poblado el R\u00edo (El Sabinito)","tipo_asentamiento":"Poblado comunal","nombre_municipio":"Aramberri","nombre_estado":"Nuevo Le\u00f3n","nombre_ciudad":"","codigo_postal_oficina":"67901","clave_estado":"19","codigo_postal_oficina_":"67901","c_cp_vacio":"","clave_tipo_asentamiento":"27","clave_municipio":"7","identificador_asentamiento":"5364","zona_asentamiento":"Rural","clave_interna_cp_ciudad":""},{"id":"88480","codigo_postal_asentamiento":"67943","nombre_asentamiento":"La Hoya de los Nogales","tipo_asentamiento":"Poblado comunal","nombre_municipio":"Aramberri","nombre_estado":"Nuevo Le\u00f3n","nombre_ciudad":"","codigo_postal_oficina":"67901","clave_estado":"19","codigo_postal_oficina_":"67901","c_cp_vacio":"","clave_tipo_asentamiento":"27","clave_municipio":"7","identificador_asentamiento":"5318","zona_asentamiento":"Rural","clave_interna_cp_ciudad":""},{"id":"88481","codigo_postal_asentamiento":"67943","nombre_asentamiento":"Callej\u00f3n de los V\u00e1zquez","tipo_asentamiento":"Poblado comunal","nombre_municipio":"Aramberri","nombre_estado":"Nuevo Le\u00f3n","nombre_ciudad":"","codigo_postal_oficina":"67901","clave_estado":"19","codigo_postal_oficina_":"67901","c_cp_vacio":"","clave_tipo_asentamiento":"27","clave_municipio":"7","identificador_asentamiento":"5241","zona_asentamiento":"Rural","clave_interna_cp_ciudad":""},{"id":"88482","codigo_postal_asentamiento":"67943","nombre_asentamiento":"Potrero del Padre (Lagunita de Gonz\u00e1lez)","tipo_asentamiento":"Poblado comunal","nombre_municipio":"Aramberri","nombre_estado":"Nuevo Le\u00f3n","nombre_ciudad":"","codigo_postal_oficina":"67901","clave_estado":"19","codigo_postal_oficina_":"67901","c_cp_vacio":"","clave_tipo_asentamiento":"27","clave_municipio":"7","identificador_asentamiento":"5366","zona_asentamiento":"Rural","clave_interna_cp_ciudad":""},{"id":"88483","codigo_postal_asentamiento":"67943","nombre_asentamiento":"Salitrillo","tipo_asentamiento":"Poblado comunal","nombre_municipio":"Aramberri","nombre_estado":"Nuevo Le\u00f3n","nombre_ciudad":"","codigo_postal_oficina":"67901","clave_estado":"19","codigo_postal_oficina_":"67901","c_cp_vacio":"","clave_tipo_asentamiento":"27","clave_municipio":"7","identificador_asentamiento":"5378","zona_asentamiento":"Rural","clave_interna_cp_ciudad":""},{"id":"88484","codigo_postal_asentamiento":"67944","nombre_asentamiento":"La Escondida","tipo_asentamiento":"Congregaci\u00f3n","nombre_municipio":"Aramberri","nombre_estado":"Nuevo Le\u00f3n","nombre_ciudad":"","codigo_postal_oficina":"67901","clave_estado":"19","codigo_postal_oficina_":"67901","c_cp_vacio":"","clave_tipo_asentamiento":"11","clave_municipio":"7","identificador_asentamiento":"2398","zona_asentamiento":"Rural","clave_interna_cp_ciudad":""},{"id":"88485","codigo_postal_asentamiento":"67944","nombre_asentamiento":"El Callej\u00f3n de la Cueva","tipo_asentamiento":"Poblado comunal","nombre_municipio":"Aramberri","nombre_estado":"Nuevo Le\u00f3n","nombre_ciudad":"","codigo_postal_oficina":"67901","clave_estado":"19","codigo_postal_oficina_":"67901","c_cp_vacio":"","clave_tipo_asentamiento":"27","clave_municipio":"7","identificador_asentamiento":"5252","zona_asentamiento":"Rural","clave_interna_cp_ciudad":""},{"id":"88486","codigo_postal_asentamiento":"67944","nombre_asentamiento":"El Gato","tipo_asentamiento":"Poblado comunal","nombre_municipio":"Aramberri","nombre_estado":"Nuevo Le\u00f3n","nombre_ciudad":"","codigo_postal_oficina":"67901","clave_estado":"19","codigo_postal_oficina_":"67901","c_cp_vacio":"","clave_tipo_asentamiento":"27","clave_municipio":"7","identificador_asentamiento":"5260","zona_asentamiento":"Rural","clave_interna_cp_ciudad":""},{"id":"88487","codigo_postal_asentamiento":"67944","nombre_asentamiento":"La Lobera","tipo_asentamiento":"Poblado comunal","nombre_municipio":"Aramberri","nombre_estado":"Nuevo Le\u00f3n","nombre_ciudad":"","codigo_postal_oficina":"67901","clave_estado":"19","codigo_postal_oficina_":"67901","c_cp_vacio":"","clave_tipo_asentamiento":"27","clave_municipio":"7","identificador_asentamiento":"5321","zona_asentamiento":"Rural","clave_interna_cp_ciudad":""},{"id":"88488","codigo_postal_asentamiento":"67944","nombre_asentamiento":"Las Mancuernas","tipo_asentamiento":"Poblado comunal","nombre_municipio":"Aramberri","nombre_estado":"Nuevo Le\u00f3n","nombre_ciudad":"","codigo_postal_oficina":"67901","clave_estado":"19","codigo_postal_oficina_":"67901","c_cp_vacio":"","clave_tipo_asentamiento":"27","clave_municipio":"7","identificador_asentamiento":"5346","zona_asentamiento":"Rural","clave_interna_cp_ciudad":""},{"id":"88489","codigo_postal_asentamiento":"67944","nombre_asentamiento":"Milpillas","tipo_asentamiento":"Poblado comunal","nombre_municipio":"Aramberri","nombre_estado":"Nuevo Le\u00f3n","nombre_ciudad":"","codigo_postal_oficina":"67901","clave_estado":"19","codigo_postal_oficina_":"67901","c_cp_vacio":"","clave_tipo_asentamiento":"27","clave_municipio":"7","identificador_asentamiento":"5357","zona_asentamiento":"Rural","clave_interna_cp_ciudad":""},{"id":"88490","codigo_postal_asentamiento":"67944","nombre_asentamiento":"La Aldea","tipo_asentamiento":"Ejido","nombre_municipio":"Aramberri","nombre_estado":"Nuevo Le\u00f3n","nombre_ciudad":"","codigo_postal_oficina":"67901","clave_estado":"19","codigo_postal_oficina_":"67901","c_cp_vacio":"","clave_tipo_asentamiento":"15","clave_municipio":"7","identificador_asentamiento":"2395","zona_asentamiento":"Rural","clave_interna_cp_ciudad":""},{"id":"88491","codigo_postal_asentamiento":"67944","nombre_asentamiento":"El Alamar","tipo_asentamiento":"Poblado comunal","nombre_municipio":"Aramberri","nombre_estado":"Nuevo Le\u00f3n","nombre_ciudad":"","codigo_postal_oficina":"67901","clave_estado":"19","codigo_postal_oficina_":"67901","c_cp_vacio":"","clave_tipo_asentamiento":"27","clave_municipio":"7","identificador_asentamiento":"5248","zona_asentamiento":"Rural","clave_interna_cp_ciudad":""},{"id":"88492","codigo_postal_asentamiento":"67944","nombre_asentamiento":"El Monal","tipo_asentamiento":"Poblado comunal","nombre_municipio":"Aramberri","nombre_estado":"Nuevo Le\u00f3n","nombre_ciudad":"","codigo_postal_oficina":"67901","clave_estado":"19","codigo_postal_oficina_":"67901","c_cp_vacio":"","clave_tipo_asentamiento":"27","clave_municipio":"7","identificador_asentamiento":"5266","zona_asentamiento":"Rural","clave_interna_cp_ciudad":""},{"id":"88493","codigo_postal_asentamiento":"67944","nombre_asentamiento":"El Refugio","tipo_asentamiento":"Poblado comunal","nombre_municipio":"Aramberri","nombre_estado":"Nuevo Le\u00f3n","nombre_ciudad":"","codigo_postal_oficina":"67901","clave_estado":"19","codigo_postal_oficina_":"67901","c_cp_vacio":"","clave_tipo_asentamiento":"27","clave_municipio":"7","identificador_asentamiento":"5281","zona_asentamiento":"Rural","clave_interna_cp_ciudad":""},{"id":"88494","codigo_postal_asentamiento":"67944","nombre_asentamiento":"Los Nogales (El Mezquital)","tipo_asentamiento":"Poblado comunal","nombre_municipio":"Aramberri","nombre_estado":"Nuevo Le\u00f3n","nombre_ciudad":"","codigo_postal_oficina":"67901","clave_estado":"19","codigo_postal_oficina_":"67901","c_cp_vacio":"","clave_tipo_asentamiento":"27","clave_municipio":"7","identificador_asentamiento":"5354","zona_asentamiento":"Rural","clave_interna_cp_ciudad":""},{"id":"88495","codigo_postal_asentamiento":"67944","nombre_asentamiento":"Los Nogales","tipo_asentamiento":"Rancher\u00eda","nombre_municipio":"Aramberri","nombre_estado":"Nuevo Le\u00f3n","nombre_ciudad":"","codigo_postal_oficina":"67901","clave_estado":"19","codigo_postal_oficina_":"67901","c_cp_vacio":"","clave_tipo_asentamiento":"29","clave_municipio":"7","identificador_asentamiento":"2397","zona_asentamiento":"Rural","clave_interna_cp_ciudad":""},{"id":"88496","codigo_postal_asentamiento":"67944","nombre_asentamiento":"Agua Delgada","tipo_asentamiento":"Poblado comunal","nombre_municipio":"Aramberri","nombre_estado":"Nuevo Le\u00f3n","nombre_ciudad":"","codigo_postal_oficina":"67901","clave_estado":"19","codigo_postal_oficina_":"67901","c_cp_vacio":"","clave_tipo_asentamiento":"27","clave_municipio":"7","identificador_asentamiento":"5235","zona_asentamiento":"Rural","clave_interna_cp_ciudad":""},{"id":"88497","codigo_postal_asentamiento":"67944","nombre_asentamiento":"El Olmo","tipo_asentamiento":"Poblado comunal","nombre_municipio":"Aramberri","nombre_estado":"Nuevo Le\u00f3n","nombre_ciudad":"","codigo_postal_oficina":"67901","clave_estado":"19","codigo_postal_oficina_":"67901","c_cp_vacio":"","clave_tipo_asentamiento":"27","clave_municipio":"7","identificador_asentamiento":"5271","zona_asentamiento":"Rural","clave_interna_cp_ciudad":""},{"id":"88498","codigo_postal_asentamiento":"67944","nombre_asentamiento":"El Realito (La Parrita)","tipo_asentamiento":"Poblado comunal","nombre_municipio":"Aramberri","nombre_estado":"Nuevo Le\u00f3n","nombre_ciudad":"","codigo_postal_oficina":"67901","clave_estado":"19","codigo_postal_oficina_":"67901","c_cp_vacio":"","clave_tipo_asentamiento":"27","clave_municipio":"7","identificador_asentamiento":"5280","zona_asentamiento":"Rural","clave_interna_cp_ciudad":""},{"id":"88499","codigo_postal_asentamiento":"67944","nombre_asentamiento":"El Rinc\u00f3n","tipo_asentamiento":"Poblado comunal","nombre_municipio":"Aramberri","nombre_estado":"Nuevo Le\u00f3n","nombre_ciudad":"","codigo_postal_oficina":"67901","clave_estado":"19","codigo_postal_oficina_":"67901","c_cp_vacio":"","clave_tipo_asentamiento":"27","clave_municipio":"7","identificador_asentamiento":"5283","zona_asentamiento":"Rural","clave_interna_cp_ciudad":""},{"id":"88500","codigo_postal_asentamiento":"67944","nombre_asentamiento":"Potrero de Zamora","tipo_asentamiento":"Poblado comunal","nombre_municipio":"Aramberri","nombre_estado":"Nuevo Le\u00f3n","nombre_ciudad":"","codigo_postal_oficina":"67901","clave_estado":"19","codigo_postal_oficina_":"67901","c_cp_vacio":"","clave_tipo_asentamiento":"27","clave_municipio":"7","identificador_asentamiento":"5365","zona_asentamiento":"Rural","clave_interna_cp_ciudad":""},{"id":"88501","codigo_postal_asentamiento":"67944","nombre_asentamiento":"Rancho Nuevo","tipo_asentamiento":"Rancher\u00eda","nombre_municipio":"Aramberri","nombre_estado":"Nuevo Le\u00f3n","nombre_ciudad":"","codigo_postal_oficina":"67901","clave_estado":"19","codigo_postal_oficina_":"67901","c_cp_vacio":"","clave_tipo_asentamiento":"29","clave_municipio":"7","identificador_asentamiento":"5374","zona_asentamiento":"Rural","clave_interna_cp_ciudad":""},{"id":"88502","codigo_postal_asentamiento":"67944","nombre_asentamiento":"Rancho Nuevo (Las Hornillas)","tipo_asentamiento":"Rancher\u00eda","nombre_municipio":"Aramberri","nombre_estado":"Nuevo Le\u00f3n","nombre_ciudad":"","codigo_postal_oficina":"67901","clave_estado":"19","codigo_postal_oficina_":"67901","c_cp_vacio":"","clave_tipo_asentamiento":"29","clave_municipio":"7","identificador_asentamiento":"5376","zona_asentamiento":"Rural","clave_interna_cp_ciudad":""},{"id":"88503","codigo_postal_asentamiento":"67944","nombre_asentamiento":"El Muerto","tipo_asentamiento":"Poblado comunal","nombre_municipio":"Aramberri","nombre_estado":"Nuevo Le\u00f3n","nombre_ciudad":"","codigo_postal_oficina":"67901","clave_estado":"19","codigo_postal_oficina_":"67901","c_cp_vacio":"","clave_tipo_asentamiento":"27","clave_municipio":"7","identificador_asentamiento":"5267","zona_asentamiento":"Rural","clave_interna_cp_ciudad":""},{"id":"88504","codigo_postal_asentamiento":"67944","nombre_asentamiento":"La Florida","tipo_asentamiento":"Poblado comunal","nombre_municipio":"Aramberri","nombre_estado":"Nuevo Le\u00f3n","nombre_ciudad":"","codigo_postal_oficina":"67901","clave_estado":"19","codigo_postal_oficina_":"67901","c_cp_vacio":"","clave_tipo_asentamiento":"27","clave_municipio":"7","identificador_asentamiento":"5316","zona_asentamiento":"Rural","clave_interna_cp_ciudad":""},{"id":"88505","codigo_postal_asentamiento":"67944","nombre_asentamiento":"El Pitacoche","tipo_asentamiento":"Poblado comunal","nombre_municipio":"Aramberri","nombre_estado":"Nuevo Le\u00f3n","nombre_ciudad":"","codigo_postal_oficina":"67901","clave_estado":"19","codigo_postal_oficina_":"67901","c_cp_vacio":"","clave_tipo_asentamiento":"27","clave_municipio":"7","identificador_asentamiento":"5274","zona_asentamiento":"Rural","clave_interna_cp_ciudad":""},{"id":"88506","codigo_postal_asentamiento":"67944","nombre_asentamiento":"Granjenal","tipo_asentamiento":"Poblado comunal","nombre_municipio":"Aramberri","nombre_estado":"Nuevo Le\u00f3n","nombre_ciudad":"","codigo_postal_oficina":"67901","clave_estado":"19","codigo_postal_oficina_":"67901","c_cp_vacio":"","clave_tipo_asentamiento":"27","clave_municipio":"7","identificador_asentamiento":"5300","zona_asentamiento":"Rural","clave_interna_cp_ciudad":""},{"id":"88507","codigo_postal_asentamiento":"67944","nombre_asentamiento":"Ojo de Agua","tipo_asentamiento":"Poblado comunal","nombre_municipio":"Aramberri","nombre_estado":"Nuevo Le\u00f3n","nombre_ciudad":"","codigo_postal_oficina":"67901","clave_estado":"19","codigo_postal_oficina_":"67901","c_cp_vacio":"","clave_tipo_asentamiento":"27","clave_municipio":"7","identificador_asentamiento":"5361","zona_asentamiento":"Rural","clave_interna_cp_ciudad":""},{"id":"88508","codigo_postal_asentamiento":"67944","nombre_asentamiento":"Las \u00c1nimas","tipo_asentamiento":"Ejido","nombre_municipio":"Aramberri","nombre_estado":"Nuevo Le\u00f3n","nombre_ciudad":"","codigo_postal_oficina":"67901","clave_estado":"19","codigo_postal_oficina_":"67901","c_cp_vacio":"","clave_tipo_asentamiento":"15","clave_municipio":"7","identificador_asentamiento":"2416","zona_asentamiento":"Rural","clave_interna_cp_ciudad":""},{"id":"88509","codigo_postal_asentamiento":"67944","nombre_asentamiento":"Puerto Carretas","tipo_asentamiento":"Poblado comunal","nombre_municipio":"Aramberri","nombre_estado":"Nuevo Le\u00f3n","nombre_ciudad":"","codigo_postal_oficina":"67901","clave_estado":"19","codigo_postal_oficina_":"67901","c_cp_vacio":"","clave_tipo_asentamiento":"27","clave_municipio":"7","identificador_asentamiento":"5370","zona_asentamiento":"Rural","clave_interna_cp_ciudad":""},{"id":"88510","codigo_postal_asentamiento":"67944","nombre_asentamiento":"El Cedrito","tipo_asentamiento":"Poblado comunal","nombre_municipio":"Aramberri","nombre_estado":"Nuevo Le\u00f3n","nombre_ciudad":"","codigo_postal_oficina":"67901","clave_estado":"19","codigo_postal_oficina_":"67901","c_cp_vacio":"","clave_tipo_asentamiento":"27","clave_municipio":"7","identificador_asentamiento":"5254","zona_asentamiento":"Rural","clave_interna_cp_ciudad":""},{"id":"88511","codigo_postal_asentamiento":"67944","nombre_asentamiento":"La Lagunita (Lagunita de los V\u00e1zquez)","tipo_asentamiento":"Poblado comunal","nombre_municipio":"Aramberri","nombre_estado":"Nuevo Le\u00f3n","nombre_ciudad":"","codigo_postal_oficina":"67901","clave_estado":"19","codigo_postal_oficina_":"67901","c_cp_vacio":"","clave_tipo_asentamiento":"27","clave_municipio":"7","identificador_asentamiento":"5320","zona_asentamiento":"Rural","clave_interna_cp_ciudad":""},{"id":"88512","codigo_postal_asentamiento":"67944","nombre_asentamiento":"Lagunita (Lagunita de los Cerda)","tipo_asentamiento":"Poblado comunal","nombre_municipio":"Aramberri","nombre_estado":"Nuevo Le\u00f3n","nombre_ciudad":"","codigo_postal_oficina":"67901","clave_estado":"19","codigo_postal_oficina_":"67901","c_cp_vacio":"","clave_tipo_asentamiento":"27","clave_municipio":"7","identificador_asentamiento":"5339","zona_asentamiento":"Rural","clave_interna_cp_ciudad":""},{"id":"88513","codigo_postal_asentamiento":"67944","nombre_asentamiento":"San Isidro","tipo_asentamiento":"Poblado comunal","nombre_municipio":"Aramberri","nombre_estado":"Nuevo Le\u00f3n","nombre_ciudad":"","codigo_postal_oficina":"67901","clave_estado":"19","codigo_postal_oficina_":"67901","c_cp_vacio":"","clave_tipo_asentamiento":"27","clave_municipio":"7","identificador_asentamiento":"5382","zona_asentamiento":"Rural","clave_interna_cp_ciudad":""},{"id":"88514","codigo_postal_asentamiento":"67944","nombre_asentamiento":"Santa Cruz","tipo_asentamiento":"Poblado comunal","nombre_municipio":"Aramberri","nombre_estado":"Nuevo Le\u00f3n","nombre_ciudad":"","codigo_postal_oficina":"67901","clave_estado":"19","codigo_postal_oficina_":"67901","c_cp_vacio":"","clave_tipo_asentamiento":"27","clave_municipio":"7","identificador_asentamiento":"5390","zona_asentamiento":"Rural","clave_interna_cp_ciudad":""},{"id":"88515","codigo_postal_asentamiento":"67944","nombre_asentamiento":"Aramberri (Brownsville)","tipo_asentamiento":"Poblado comunal","nombre_municipio":"Aramberri","nombre_estado":"Nuevo Le\u00f3n","nombre_ciudad":"","codigo_postal_oficina":"67901","clave_estado":"19","codigo_postal_oficina_":"67901","c_cp_vacio":"","clave_tipo_asentamiento":"27","clave_municipio":"7","identificador_asentamiento":"5237","zona_asentamiento":"Rural","clave_interna_cp_ciudad":""},{"id":"88516","codigo_postal_asentamiento":"67944","nombre_asentamiento":"El Molino","tipo_asentamiento":"Poblado comunal","nombre_municipio":"Aramberri","nombre_estado":"Nuevo Le\u00f3n","nombre_ciudad":"","codigo_postal_oficina":"67901","clave_estado":"19","codigo_postal_oficina_":"67901","c_cp_vacio":"","clave_tipo_asentamiento":"27","clave_municipio":"7","identificador_asentamiento":"5265","zona_asentamiento":"Rural","clave_interna_cp_ciudad":""},{"id":"88517","codigo_postal_asentamiento":"67944","nombre_asentamiento":"El Pitacoche (La Tinaja)","tipo_asentamiento":"Poblado comunal","nombre_municipio":"Aramberri","nombre_estado":"Nuevo Le\u00f3n","nombre_ciudad":"","codigo_postal_oficina":"67901","clave_estado":"19","codigo_postal_oficina_":"67901","c_cp_vacio":"","clave_tipo_asentamiento":"27","clave_municipio":"7","identificador_asentamiento":"5275","zona_asentamiento":"Rural","clave_interna_cp_ciudad":""},{"id":"88518","codigo_postal_asentamiento":"67944","nombre_asentamiento":"El Talco","tipo_asentamiento":"Poblado comunal","nombre_municipio":"Aramberri","nombre_estado":"Nuevo Le\u00f3n","nombre_ciudad":"","codigo_postal_oficina":"67901","clave_estado":"19","codigo_postal_oficina_":"67901","c_cp_vacio":"","clave_tipo_asentamiento":"27","clave_municipio":"7","identificador_asentamiento":"5291","zona_asentamiento":"Rural","clave_interna_cp_ciudad":""},{"id":"88519","codigo_postal_asentamiento":"67944","nombre_asentamiento":"La Carpinter\u00eda","tipo_asentamiento":"Poblado comunal","nombre_municipio":"Aramberri","nombre_estado":"Nuevo Le\u00f3n","nombre_ciudad":"","codigo_postal_oficina":"67901","clave_estado":"19","codigo_postal_oficina_":"67901","c_cp_vacio":"","clave_tipo_asentamiento":"27","clave_municipio":"7","identificador_asentamiento":"5313","zona_asentamiento":"Rural","clave_interna_cp_ciudad":""},{"id":"88520","codigo_postal_asentamiento":"67944","nombre_asentamiento":"Salitrillo","tipo_asentamiento":"Poblado comunal","nombre_municipio":"Aramberri","nombre_estado":"Nuevo Le\u00f3n","nombre_ciudad":"","codigo_postal_oficina":"67901","clave_estado":"19","codigo_postal_oficina_":"67901","c_cp_vacio":"","clave_tipo_asentamiento":"27","clave_municipio":"7","identificador_asentamiento":"5377","zona_asentamiento":"Rural","clave_interna_cp_ciudad":""},{"id":"88521","codigo_postal_asentamiento":"67945","nombre_asentamiento":"La Soledad (Rusia)","tipo_asentamiento":"Ejido","nombre_municipio":"Aramberri","nombre_estado":"Nuevo Le\u00f3n","nombre_ciudad":"","codigo_postal_oficina":"67901","clave_estado":"19","codigo_postal_oficina_":"67901","c_cp_vacio":"","clave_tipo_asentamiento":"15","clave_municipio":"7","identificador_asentamiento":"2406","zona_asentamiento":"Rural","clave_interna_cp_ciudad":""},{"id":"88522","codigo_postal_asentamiento":"67945","nombre_asentamiento":"El Carrizalillo","tipo_asentamiento":"Poblado comunal","nombre_municipio":"Aramberri","nombre_estado":"Nuevo Le\u00f3n","nombre_ciudad":"","codigo_postal_oficina":"67901","clave_estado":"19","codigo_postal_oficina_":"67901","c_cp_vacio":"","clave_tipo_asentamiento":"27","clave_municipio":"7","identificador_asentamiento":"5253","zona_asentamiento":"Rural","clave_interna_cp_ciudad":""},{"id":"88523","codigo_postal_asentamiento":"67945","nombre_asentamiento":"La Nueva Reforma (Buenos Aires)","tipo_asentamiento":"Poblado comunal","nombre_municipio":"Aramberri","nombre_estado":"Nuevo Le\u00f3n","nombre_ciudad":"","codigo_postal_oficina":"67901","clave_estado":"19","codigo_postal_oficina_":"67901","c_cp_vacio":"","clave_tipo_asentamiento":"27","clave_municipio":"7","identificador_asentamiento":"5325","zona_asentamiento":"Rural","clave_interna_cp_ciudad":""},{"id":"88524","codigo_postal_asentamiento":"67945","nombre_asentamiento":"La Sabanilla","tipo_asentamiento":"Poblado comunal","nombre_municipio":"Aramberri","nombre_estado":"Nuevo Le\u00f3n","nombre_ciudad":"","codigo_postal_oficina":"67901","clave_estado":"19","codigo_postal_oficina_":"67901","c_cp_vacio":"","clave_tipo_asentamiento":"27","clave_municipio":"7","identificador_asentamiento":"5334","zona_asentamiento":"Rural","clave_interna_cp_ciudad":""},{"id":"88525","codigo_postal_asentamiento":"67945","nombre_asentamiento":"Sandia el Chico","tipo_asentamiento":"Poblado comunal","nombre_municipio":"Aramberri","nombre_estado":"Nuevo Le\u00f3n","nombre_ciudad":"","codigo_postal_oficina":"67901","clave_estado":"19","codigo_postal_oficina_":"67901","c_cp_vacio":"","clave_tipo_asentamiento":"27","clave_municipio":"7","identificador_asentamiento":"5388","zona_asentamiento":"Rural","clave_interna_cp_ciudad":""},{"id":"88526","codigo_postal_asentamiento":"67945","nombre_asentamiento":"El Tigre","tipo_asentamiento":"Poblado comunal","nombre_municipio":"Aramberri","nombre_estado":"Nuevo Le\u00f3n","nombre_ciudad":"","codigo_postal_oficina":"67901","clave_estado":"19","codigo_postal_oficina_":"67901","c_cp_vacio":"","clave_tipo_asentamiento":"27","clave_municipio":"7","identificador_asentamiento":"5294","zona_asentamiento":"Rural","clave_interna_cp_ciudad":""},{"id":"88527","codigo_postal_asentamiento":"67945","nombre_asentamiento":"El Tepoz\u00e1n","tipo_asentamiento":"Poblado comunal","nombre_municipio":"Aramberri","nombre_estado":"Nuevo Le\u00f3n","nombre_ciudad":"","codigo_postal_oficina":"67901","clave_estado":"19","codigo_postal_oficina_":"67901","c_cp_vacio":"","clave_tipo_asentamiento":"27","clave_municipio":"7","identificador_asentamiento":"5293","zona_asentamiento":"Rural","clave_interna_cp_ciudad":""},{"id":"88528","codigo_postal_asentamiento":"67946","nombre_asentamiento":"Cedritos","tipo_asentamiento":"Poblado comunal","nombre_municipio":"Aramberri","nombre_estado":"Nuevo Le\u00f3n","nombre_ciudad":"","codigo_postal_oficina":"67901","clave_estado":"19","codigo_postal_oficina_":"67901","c_cp_vacio":"","clave_tipo_asentamiento":"27","clave_municipio":"7","identificador_asentamiento":"5242","zona_asentamiento":"Rural","clave_interna_cp_ciudad":""},{"id":"88529","codigo_postal_asentamiento":"67946","nombre_asentamiento":"La V\u00edbora","tipo_asentamiento":"Poblado comunal","nombre_municipio":"Aramberri","nombre_estado":"Nuevo Le\u00f3n","nombre_ciudad":"","codigo_postal_oficina":"67901","clave_estado":"19","codigo_postal_oficina_":"67901","c_cp_vacio":"","clave_tipo_asentamiento":"27","clave_municipio":"7","identificador_asentamiento":"5337","zona_asentamiento":"Rural","clave_interna_cp_ciudad":""},{"id":"88530","codigo_postal_asentamiento":"67946","nombre_asentamiento":"La Sabanilla","tipo_asentamiento":"Poblado comunal","nombre_municipio":"Aramberri","nombre_estado":"Nuevo Le\u00f3n","nombre_ciudad":"","codigo_postal_oficina":"67901","clave_estado":"19","codigo_postal_oficina_":"67901","c_cp_vacio":"","clave_tipo_asentamiento":"27","clave_municipio":"7","identificador_asentamiento":"5333","zona_asentamiento":"Rural","clave_interna_cp_ciudad":""},{"id":"88531","codigo_postal_asentamiento":"67947","nombre_asentamiento":"Pozo Dos","tipo_asentamiento":"Poblado comunal","nombre_municipio":"Aramberri","nombre_estado":"Nuevo Le\u00f3n","nombre_ciudad":"","codigo_postal_oficina":"67901","clave_estado":"19","codigo_postal_oficina_":"67901","c_cp_vacio":"","clave_tipo_asentamiento":"27","clave_municipio":"7","identificador_asentamiento":"5367","zona_asentamiento":"Rural","clave_interna_cp_ciudad":""},{"id":"88532","codigo_postal_asentamiento":"67947","nombre_asentamiento":"Puentes (San Juan y Puentes)","tipo_asentamiento":"Ejido","nombre_municipio":"Aramberri","nombre_estado":"Nuevo Le\u00f3n","nombre_ciudad":"","codigo_postal_oficina":"67901","clave_estado":"19","codigo_postal_oficina_":"67901","c_cp_vacio":"","clave_tipo_asentamiento":"15","clave_municipio":"7","identificador_asentamiento":"2405","zona_asentamiento":"Rural","clave_interna_cp_ciudad":""},{"id":"88533","codigo_postal_asentamiento":"67947","nombre_asentamiento":"La Pe\u00f1a","tipo_asentamiento":"Poblado comunal","nombre_municipio":"Aramberri","nombre_estado":"Nuevo Le\u00f3n","nombre_ciudad":"","codigo_postal_oficina":"67901","clave_estado":"19","codigo_postal_oficina_":"67901","c_cp_vacio":"","clave_tipo_asentamiento":"27","clave_municipio":"7","identificador_asentamiento":"5329","zona_asentamiento":"Rural","clave_interna_cp_ciudad":""},{"id":"88534","codigo_postal_asentamiento":"67947","nombre_asentamiento":"San Juan de Avil\u00e9s","tipo_asentamiento":"Hacienda","nombre_municipio":"Aramberri","nombre_estado":"Nuevo Le\u00f3n","nombre_ciudad":"","codigo_postal_oficina":"67901","clave_estado":"19","codigo_postal_oficina_":"67901","c_cp_vacio":"","clave_tipo_asentamiento":"24","clave_municipio":"7","identificador_asentamiento":"2420","zona_asentamiento":"Rural","clave_interna_cp_ciudad":""},{"id":"88535","codigo_postal_asentamiento":"67947","nombre_asentamiento":"La Trinidad","tipo_asentamiento":"Ejido","nombre_municipio":"Aramberri","nombre_estado":"Nuevo Le\u00f3n","nombre_ciudad":"","codigo_postal_oficina":"67901","clave_estado":"19","codigo_postal_oficina_":"67901","c_cp_vacio":"","clave_tipo_asentamiento":"15","clave_municipio":"7","identificador_asentamiento":"2396","zona_asentamiento":"Rural","clave_interna_cp_ciudad":""},{"id":"88536","codigo_postal_asentamiento":"67947","nombre_asentamiento":"El Pinalito","tipo_asentamiento":"Poblado comunal","nombre_municipio":"Aramberri","nombre_estado":"Nuevo Le\u00f3n","nombre_ciudad":"","codigo_postal_oficina":"67901","clave_estado":"19","codigo_postal_oficina_":"67901","c_cp_vacio":"","clave_tipo_asentamiento":"27","clave_municipio":"7","identificador_asentamiento":"5273","zona_asentamiento":"Rural","clave_interna_cp_ciudad":""},{"id":"88537","codigo_postal_asentamiento":"67947","nombre_asentamiento":"La Rosita (Los Llanitos)","tipo_asentamiento":"Poblado comunal","nombre_municipio":"Aramberri","nombre_estado":"Nuevo Le\u00f3n","nombre_ciudad":"","codigo_postal_oficina":"67901","clave_estado":"19","codigo_postal_oficina_":"67901","c_cp_vacio":"","clave_tipo_asentamiento":"27","clave_municipio":"7","identificador_asentamiento":"5332","zona_asentamiento":"Rural","clave_interna_cp_ciudad":""},{"id":"88538","codigo_postal_asentamiento":"67947","nombre_asentamiento":"Dolores Palmita","tipo_asentamiento":"Poblado comunal","nombre_municipio":"Aramberri","nombre_estado":"Nuevo Le\u00f3n","nombre_ciudad":"","codigo_postal_oficina":"67901","clave_estado":"19","codigo_postal_oficina_":"67901","c_cp_vacio":"","clave_tipo_asentamiento":"27","clave_municipio":"7","identificador_asentamiento":"5246","zona_asentamiento":"Rural","clave_interna_cp_ciudad":""},{"id":"88539","codigo_postal_asentamiento":"67948","nombre_asentamiento":"San Juanito de Res\u00e9ndiz","tipo_asentamiento":"Poblado comunal","nombre_municipio":"Aramberri","nombre_estado":"Nuevo Le\u00f3n","nombre_ciudad":"","codigo_postal_oficina":"67901","clave_estado":"19","codigo_postal_oficina_":"67901","c_cp_vacio":"","clave_tipo_asentamiento":"27","clave_municipio":"7","identificador_asentamiento":"5384","zona_asentamiento":"Rural","clave_interna_cp_ciudad":""},{"id":"88540","codigo_postal_asentamiento":"67948","nombre_asentamiento":"San Rafael de los Cortez","tipo_asentamiento":"Poblado comunal","nombre_municipio":"Aramberri","nombre_estado":"Nuevo Le\u00f3n","nombre_ciudad":"","codigo_postal_oficina":"67901","clave_estado":"19","codigo_postal_oficina_":"67901","c_cp_vacio":"","clave_tipo_asentamiento":"27","clave_municipio":"7","identificador_asentamiento":"5386","zona_asentamiento":"Rural","clave_interna_cp_ciudad":""},{"id":"88541","codigo_postal_asentamiento":"67948","nombre_asentamiento":"San Rafael de los Cortez (La Cuesta)","tipo_asentamiento":"Poblado comunal","nombre_municipio":"Aramberri","nombre_estado":"Nuevo Le\u00f3n","nombre_ciudad":"","codigo_postal_oficina":"67901","clave_estado":"19","codigo_postal_oficina_":"67901","c_cp_vacio":"","clave_tipo_asentamiento":"27","clave_municipio":"7","identificador_asentamiento":"5387","zona_asentamiento":"Rural","clave_interna_cp_ciudad":""},{"id":"88542","codigo_postal_asentamiento":"67948","nombre_asentamiento":"Santa Rita","tipo_asentamiento":"Poblado comunal","nombre_municipio":"Aramberri","nombre_estado":"Nuevo Le\u00f3n","nombre_ciudad":"","codigo_postal_oficina":"67901","clave_estado":"19","codigo_postal_oficina_":"67901","c_cp_vacio":"","clave_tipo_asentamiento":"27","clave_municipio":"7","identificador_asentamiento":"5391","zona_asentamiento":"Rural","clave_interna_cp_ciudad":""},{"id":"88543","codigo_postal_asentamiento":"67948","nombre_asentamiento":"Agua de Mata","tipo_asentamiento":"Poblado comunal","nombre_municipio":"Aramberri","nombre_estado":"Nuevo Le\u00f3n","nombre_ciudad":"","codigo_postal_oficina":"67901","clave_estado":"19","codigo_postal_oficina_":"67901","c_cp_vacio":"","clave_tipo_asentamiento":"27","clave_municipio":"7","identificador_asentamiento":"5234","zona_asentamiento":"Rural","clave_interna_cp_ciudad":""},{"id":"88544","codigo_postal_asentamiento":"67948","nombre_asentamiento":"Cuartitos y Marmolejo (Parada Marmolejo)","tipo_asentamiento":"Poblado comunal","nombre_municipio":"Aramberri","nombre_estado":"Nuevo Le\u00f3n","nombre_ciudad":"","codigo_postal_oficina":"67901","clave_estado":"19","codigo_postal_oficina_":"67901","c_cp_vacio":"","clave_tipo_asentamiento":"27","clave_municipio":"7","identificador_asentamiento":"5245","zona_asentamiento":"Rural","clave_interna_cp_ciudad":""},{"id":"88545","codigo_postal_asentamiento":"67948","nombre_asentamiento":"El Anillo","tipo_asentamiento":"Poblado comunal","nombre_municipio":"Aramberri","nombre_estado":"Nuevo Le\u00f3n","nombre_ciudad":"","codigo_postal_oficina":"67901","clave_estado":"19","codigo_postal_oficina_":"67901","c_cp_vacio":"","clave_tipo_asentamiento":"27","clave_municipio":"7","identificador_asentamiento":"5249","zona_asentamiento":"Rural","clave_interna_cp_ciudad":""},{"id":"88546","codigo_postal_asentamiento":"67948","nombre_asentamiento":"El Mezquital","tipo_asentamiento":"Poblado comunal","nombre_municipio":"Aramberri","nombre_estado":"Nuevo Le\u00f3n","nombre_ciudad":"","codigo_postal_oficina":"67901","clave_estado":"19","codigo_postal_oficina_":"67901","c_cp_vacio":"","clave_tipo_asentamiento":"27","clave_municipio":"7","identificador_asentamiento":"5264","zona_asentamiento":"Rural","clave_interna_cp_ciudad":""},{"id":"88547","codigo_postal_asentamiento":"67948","nombre_asentamiento":"El Porvenir","tipo_asentamiento":"Poblado comunal","nombre_municipio":"Aramberri","nombre_estado":"Nuevo Le\u00f3n","nombre_ciudad":"","codigo_postal_oficina":"67901","clave_estado":"19","codigo_postal_oficina_":"67901","c_cp_vacio":"","clave_tipo_asentamiento":"27","clave_municipio":"7","identificador_asentamiento":"5276","zona_asentamiento":"Rural","clave_interna_cp_ciudad":""},{"id":"88548","codigo_postal_asentamiento":"67948","nombre_asentamiento":"La Palmita","tipo_asentamiento":"Poblado comunal","nombre_municipio":"Aramberri","nombre_estado":"Nuevo Le\u00f3n","nombre_ciudad":"","codigo_postal_oficina":"67901","clave_estado":"19","codigo_postal_oficina_":"67901","c_cp_vacio":"","clave_tipo_asentamiento":"27","clave_municipio":"7","identificador_asentamiento":"5327","zona_asentamiento":"Rural","clave_interna_cp_ciudad":""},{"id":"88549","codigo_postal_asentamiento":"67948","nombre_asentamiento":"Laguna de Bocacelly","tipo_asentamiento":"Poblado comunal","nombre_municipio":"Aramberri","nombre_estado":"Nuevo Le\u00f3n","nombre_ciudad":"","codigo_postal_oficina":"67901","clave_estado":"19","codigo_postal_oficina_":"67901","c_cp_vacio":"","clave_tipo_asentamiento":"27","clave_municipio":"7","identificador_asentamiento":"5338","zona_asentamiento":"Rural","clave_interna_cp_ciudad":""},{"id":"88550","codigo_postal_asentamiento":"67948","nombre_asentamiento":"San Juan","tipo_asentamiento":"Poblado comunal","nombre_municipio":"Aramberri","nombre_estado":"Nuevo Le\u00f3n","nombre_ciudad":"","codigo_postal_oficina":"67901","clave_estado":"19","codigo_postal_oficina_":"67901","c_cp_vacio":"","clave_tipo_asentamiento":"27","clave_municipio":"7","identificador_asentamiento":"5383","zona_asentamiento":"Rural","clave_interna_cp_ciudad":""},{"id":"88551","codigo_postal_asentamiento":"67948","nombre_asentamiento":"El Calichal","tipo_asentamiento":"Poblado comunal","nombre_municipio":"Aramberri","nombre_estado":"Nuevo Le\u00f3n","nombre_ciudad":"","codigo_postal_oficina":"67901","clave_estado":"19","codigo_postal_oficina_":"67901","c_cp_vacio":"","clave_tipo_asentamiento":"27","clave_municipio":"7","identificador_asentamiento":"5251","zona_asentamiento":"Rural","clave_interna_cp_ciudad":""},{"id":"88552","codigo_postal_asentamiento":"67948","nombre_asentamiento":"El Tej\u00f3n","tipo_asentamiento":"Poblado comunal","nombre_municipio":"Aramberri","nombre_estado":"Nuevo Le\u00f3n","nombre_ciudad":"","codigo_postal_oficina":"67901","clave_estado":"19","codigo_postal_oficina_":"67901","c_cp_vacio":"","clave_tipo_asentamiento":"27","clave_municipio":"7","identificador_asentamiento":"5292","zona_asentamiento":"Rural","clave_interna_cp_ciudad":""},{"id":"88553","codigo_postal_asentamiento":"67948","nombre_asentamiento":"Ojo de Agua","tipo_asentamiento":"Poblado comunal","nombre_municipio":"Aramberri","nombre_estado":"Nuevo Le\u00f3n","nombre_ciudad":"","codigo_postal_oficina":"67901","clave_estado":"19","codigo_postal_oficina_":"67901","c_cp_vacio":"","clave_tipo_asentamiento":"27","clave_municipio":"7","identificador_asentamiento":"5360","zona_asentamiento":"Rural","clave_interna_cp_ciudad":""},{"id":"88554","codigo_postal_asentamiento":"67948","nombre_asentamiento":"San Rafael de los Cortes (Las Cruces)","tipo_asentamiento":"Ejido","nombre_municipio":"Aramberri","nombre_estado":"Nuevo Le\u00f3n","nombre_ciudad":"","codigo_postal_oficina":"67901","clave_estado":"19","codigo_postal_oficina_":"67901","c_cp_vacio":"","clave_tipo_asentamiento":"15","clave_municipio":"7","identificador_asentamiento":"2401","zona_asentamiento":"Rural","clave_interna_cp_ciudad":""},{"id":"88555","codigo_postal_asentamiento":"67948","nombre_asentamiento":"Los Cuartitos","tipo_asentamiento":"Poblado comunal","nombre_municipio":"Aramberri","nombre_estado":"Nuevo Le\u00f3n","nombre_ciudad":"","codigo_postal_oficina":"67901","clave_estado":"19","codigo_postal_oficina_":"67901","c_cp_vacio":"","clave_tipo_asentamiento":"27","clave_municipio":"7","identificador_asentamiento":"5352","zona_asentamiento":"Rural","clave_interna_cp_ciudad":""},{"id":"88556","codigo_postal_asentamiento":"67948","nombre_asentamiento":"El Porvenir","tipo_asentamiento":"Ejido","nombre_municipio":"Aramberri","nombre_estado":"Nuevo Le\u00f3n","nombre_ciudad":"","codigo_postal_oficina":"67901","clave_estado":"19","codigo_postal_oficina_":"67901","c_cp_vacio":"","clave_tipo_asentamiento":"15","clave_municipio":"7","identificador_asentamiento":"2402","zona_asentamiento":"Rural","clave_interna_cp_ciudad":""},{"id":"88557","codigo_postal_asentamiento":"67948","nombre_asentamiento":"Joyas y Anteojitos","tipo_asentamiento":"Poblado comunal","nombre_municipio":"Aramberri","nombre_estado":"Nuevo Le\u00f3n","nombre_ciudad":"","codigo_postal_oficina":"67901","clave_estado":"19","codigo_postal_oficina_":"67901","c_cp_vacio":"","clave_tipo_asentamiento":"27","clave_municipio":"7","identificador_asentamiento":"5306","zona_asentamiento":"Rural","clave_interna_cp_ciudad":""},{"id":"88558","codigo_postal_asentamiento":"67948","nombre_asentamiento":"Santa Ana","tipo_asentamiento":"Poblado comunal","nombre_municipio":"Aramberri","nombre_estado":"Nuevo Le\u00f3n","nombre_ciudad":"","codigo_postal_oficina":"67901","clave_estado":"19","codigo_postal_oficina_":"67901","c_cp_vacio":"","clave_tipo_asentamiento":"27","clave_municipio":"7","identificador_asentamiento":"5389","zona_asentamiento":"Rural","clave_interna_cp_ciudad":""},{"id":"88559","codigo_postal_asentamiento":"67948","nombre_asentamiento":"La Esperanza","tipo_asentamiento":"Ejido","nombre_municipio":"Aramberri","nombre_estado":"Nuevo Le\u00f3n","nombre_ciudad":"","codigo_postal_oficina":"67901","clave_estado":"19","codigo_postal_oficina_":"67901","c_cp_vacio":"","clave_tipo_asentamiento":"15","clave_municipio":"7","identificador_asentamiento":"2404","zona_asentamiento":"Rural","clave_interna_cp_ciudad":""},{"id":"88560","codigo_postal_asentamiento":"67948","nombre_asentamiento":"Aranjuez","tipo_asentamiento":"Poblado comunal","nombre_municipio":"Aramberri","nombre_estado":"Nuevo Le\u00f3n","nombre_ciudad":"","codigo_postal_oficina":"67901","clave_estado":"19","codigo_postal_oficina_":"67901","c_cp_vacio":"","clave_tipo_asentamiento":"27","clave_municipio":"7","identificador_asentamiento":"5238","zona_asentamiento":"Rural","clave_interna_cp_ciudad":""},{"id":"88561","codigo_postal_asentamiento":"67948","nombre_asentamiento":"Las Virgenes","tipo_asentamiento":"Poblado comunal","nombre_municipio":"Aramberri","nombre_estado":"Nuevo Le\u00f3n","nombre_ciudad":"","codigo_postal_oficina":"67901","clave_estado":"19","codigo_postal_oficina_":"67901","c_cp_vacio":"","clave_tipo_asentamiento":"27","clave_municipio":"7","identificador_asentamiento":"5351","zona_asentamiento":"Rural","clave_interna_cp_ciudad":""},{"id":"88562","codigo_postal_asentamiento":"67948","nombre_asentamiento":"Hoya de Bocacelly","tipo_asentamiento":"Rancher\u00eda","nombre_municipio":"Aramberri","nombre_estado":"Nuevo Le\u00f3n","nombre_ciudad":"","codigo_postal_oficina":"67901","clave_estado":"19","codigo_postal_oficina_":"67901","c_cp_vacio":"","clave_tipo_asentamiento":"29","clave_municipio":"7","identificador_asentamiento":"2399","zona_asentamiento":"Rural","clave_interna_cp_ciudad":""},{"id":"88563","codigo_postal_asentamiento":"67948","nombre_asentamiento":"Pedregosa","tipo_asentamiento":"Poblado comunal","nombre_municipio":"Aramberri","nombre_estado":"Nuevo Le\u00f3n","nombre_ciudad":"","codigo_postal_oficina":"67901","clave_estado":"19","codigo_postal_oficina_":"67901","c_cp_vacio":"","clave_tipo_asentamiento":"27","clave_municipio":"7","identificador_asentamiento":"5363","zona_asentamiento":"Rural","clave_interna_cp_ciudad":""},{"id":"88564","codigo_postal_asentamiento":"67950","nombre_asentamiento":"Puentes","tipo_asentamiento":"Congregaci\u00f3n","nombre_municipio":"Aramberri","nombre_estado":"Nuevo Le\u00f3n","nombre_ciudad":"","codigo_postal_oficina":"67851","clave_estado":"19","codigo_postal_oficina_":"67851","c_cp_vacio":"","clave_tipo_asentamiento":"11","clave_municipio":"7","identificador_asentamiento":"2408","zona_asentamiento":"Rural","clave_interna_cp_ciudad":""},{"id":"88565","codigo_postal_asentamiento":"67950","nombre_asentamiento":"La Ascensi\u00f3n","tipo_asentamiento":"Rancher\u00eda","nombre_municipio":"Aramberri","nombre_estado":"Nuevo Le\u00f3n","nombre_ciudad":"","codigo_postal_oficina":"67851","clave_estado":"19","codigo_postal_oficina_":"67851","c_cp_vacio":"","clave_tipo_asentamiento":"29","clave_municipio":"7","identificador_asentamiento":"2407","zona_asentamiento":"Rural","clave_interna_cp_ciudad":""},{"id":"88566","codigo_postal_asentamiento":"67953","nombre_asentamiento":"Presa de Anteojitos","tipo_asentamiento":"Poblado comunal","nombre_municipio":"Aramberri","nombre_estado":"Nuevo Le\u00f3n","nombre_ciudad":"","codigo_postal_oficina":"67851","clave_estado":"19","codigo_postal_oficina_":"67851","c_cp_vacio":"","clave_tipo_asentamiento":"27","clave_municipio":"7","identificador_asentamiento":"5368","zona_asentamiento":"Rural","clave_interna_cp_ciudad":""},{"id":"88567","codigo_postal_asentamiento":"67953","nombre_asentamiento":"Puerto de Anteojitos","tipo_asentamiento":"Poblado comunal","nombre_municipio":"Aramberri","nombre_estado":"Nuevo Le\u00f3n","nombre_ciudad":"","codigo_postal_oficina":"67851","clave_estado":"19","codigo_postal_oficina_":"67851","c_cp_vacio":"","clave_tipo_asentamiento":"27","clave_municipio":"7","identificador_asentamiento":"5371","zona_asentamiento":"Rural","clave_interna_cp_ciudad":""},{"id":"88568","codigo_postal_asentamiento":"67953","nombre_asentamiento":"La Laguna","tipo_asentamiento":"Poblado comunal","nombre_municipio":"Aramberri","nombre_estado":"Nuevo Le\u00f3n","nombre_ciudad":"","codigo_postal_oficina":"67851","clave_estado":"19","codigo_postal_oficina_":"67851","c_cp_vacio":"","clave_tipo_asentamiento":"27","clave_municipio":"7","identificador_asentamiento":"5319","zona_asentamiento":"Rural","clave_interna_cp_ciudad":""},{"id":"88569","codigo_postal_asentamiento":"67953","nombre_asentamiento":"La Reforma","tipo_asentamiento":"Poblado comunal","nombre_municipio":"Aramberri","nombre_estado":"Nuevo Le\u00f3n","nombre_ciudad":"","codigo_postal_oficina":"67851","clave_estado":"19","codigo_postal_oficina_":"67851","c_cp_vacio":"","clave_tipo_asentamiento":"27","clave_municipio":"7","identificador_asentamiento":"5330","zona_asentamiento":"Rural","clave_interna_cp_ciudad":""},{"id":"88570","codigo_postal_asentamiento":"67953","nombre_asentamiento":"San Rafael del Llano","tipo_asentamiento":"Rancher\u00eda","nombre_municipio":"Aramberri","nombre_estado":"Nuevo Le\u00f3n","nombre_ciudad":"","codigo_postal_oficina":"67851","clave_estado":"19","codigo_postal_oficina_":"67851","c_cp_vacio":"","clave_tipo_asentamiento":"29","clave_municipio":"7","identificador_asentamiento":"2422","zona_asentamiento":"Rural","clave_interna_cp_ciudad":""},{"id":"88571","codigo_postal_asentamiento":"67953","nombre_asentamiento":"La Ascensi\u00f3n (Esteban Salazar)","tipo_asentamiento":"Poblado comunal","nombre_municipio":"Aramberri","nombre_estado":"Nuevo Le\u00f3n","nombre_ciudad":"","codigo_postal_oficina":"67851","clave_estado":"19","codigo_postal_oficina_":"67851","c_cp_vacio":"","clave_tipo_asentamiento":"27","clave_municipio":"7","identificador_asentamiento":"5309","zona_asentamiento":"Rural","clave_interna_cp_ciudad":""},{"id":"88572","codigo_postal_asentamiento":"67953","nombre_asentamiento":"El Coyote","tipo_asentamiento":"Poblado comunal","nombre_municipio":"Aramberri","nombre_estado":"Nuevo Le\u00f3n","nombre_ciudad":"","codigo_postal_oficina":"67851","clave_estado":"19","codigo_postal_oficina_":"67851","c_cp_vacio":"","clave_tipo_asentamiento":"27","clave_municipio":"7","identificador_asentamiento":"5255","zona_asentamiento":"Rural","clave_interna_cp_ciudad":""},{"id":"88573","codigo_postal_asentamiento":"67953","nombre_asentamiento":"Milpa Vieja (San Manuel)","tipo_asentamiento":"Poblado comunal","nombre_municipio":"Aramberri","nombre_estado":"Nuevo Le\u00f3n","nombre_ciudad":"","codigo_postal_oficina":"67851","clave_estado":"19","codigo_postal_oficina_":"67851","c_cp_vacio":"","clave_tipo_asentamiento":"27","clave_municipio":"7","identificador_asentamiento":"5356","zona_asentamiento":"Rural","clave_interna_cp_ciudad":""},{"id":"88574","codigo_postal_asentamiento":"67953","nombre_asentamiento":"San Joaqu\u00edn de Soto","tipo_asentamiento":"Ejido","nombre_municipio":"Aramberri","nombre_estado":"Nuevo Le\u00f3n","nombre_ciudad":"","codigo_postal_oficina":"67851","clave_estado":"19","codigo_postal_oficina_":"67851","c_cp_vacio":"","clave_tipo_asentamiento":"15","clave_municipio":"7","identificador_asentamiento":"2409","zona_asentamiento":"Rural","clave_interna_cp_ciudad":""},{"id":"88575","codigo_postal_asentamiento":"67953","nombre_asentamiento":"El Derramadero","tipo_asentamiento":"Poblado comunal","nombre_municipio":"Aramberri","nombre_estado":"Nuevo Le\u00f3n","nombre_ciudad":"","codigo_postal_oficina":"67851","clave_estado":"19","codigo_postal_oficina_":"67851","c_cp_vacio":"","clave_tipo_asentamiento":"27","clave_municipio":"7","identificador_asentamiento":"5258","zona_asentamiento":"Rural","clave_interna_cp_ciudad":""},{"id":"88576","codigo_postal_asentamiento":"67954","nombre_asentamiento":"La Victoria (Los \u00c1ngeles)","tipo_asentamiento":"Ejido","nombre_municipio":"Aramberri","nombre_estado":"Nuevo Le\u00f3n","nombre_ciudad":"","codigo_postal_oficina":"67851","clave_estado":"19","codigo_postal_oficina_":"67851","c_cp_vacio":"","clave_tipo_asentamiento":"15","clave_municipio":"7","identificador_asentamiento":"2419","zona_asentamiento":"Rural","clave_interna_cp_ciudad":""},{"id":"88577","codigo_postal_asentamiento":"67954","nombre_asentamiento":"Erasmo V\u00e1zquez","tipo_asentamiento":"Poblado comunal","nombre_municipio":"Aramberri","nombre_estado":"Nuevo Le\u00f3n","nombre_ciudad":"","codigo_postal_oficina":"67851","clave_estado":"19","codigo_postal_oficina_":"67851","c_cp_vacio":"","clave_tipo_asentamiento":"27","clave_municipio":"7","identificador_asentamiento":"5296","zona_asentamiento":"Rural","clave_interna_cp_ciudad":""},{"id":"88578","codigo_postal_asentamiento":"67954","nombre_asentamiento":"El Puerto","tipo_asentamiento":"Poblado comunal","nombre_municipio":"Aramberri","nombre_estado":"Nuevo Le\u00f3n","nombre_ciudad":"","codigo_postal_oficina":"67851","clave_estado":"19","codigo_postal_oficina_":"67851","c_cp_vacio":"","clave_tipo_asentamiento":"27","clave_municipio":"7","identificador_asentamiento":"5278","zona_asentamiento":"Rural","clave_interna_cp_ciudad":""},{"id":"88579","codigo_postal_asentamiento":"67954","nombre_asentamiento":"Sandia (Sandi el Grande)","tipo_asentamiento":"Ejido","nombre_municipio":"Aramberri","nombre_estado":"Nuevo Le\u00f3n","nombre_ciudad":"","codigo_postal_oficina":"67851","clave_estado":"19","codigo_postal_oficina_":"67851","c_cp_vacio":"","clave_tipo_asentamiento":"15","clave_municipio":"7","identificador_asentamiento":"2410","zona_asentamiento":"Rural","clave_interna_cp_ciudad":""},{"id":"88580","codigo_postal_asentamiento":"67954","nombre_asentamiento":"Las Presas","tipo_asentamiento":"Poblado comunal","nombre_municipio":"Aramberri","nombre_estado":"Nuevo Le\u00f3n","nombre_ciudad":"","codigo_postal_oficina":"67851","clave_estado":"19","codigo_postal_oficina_":"67851","c_cp_vacio":"","clave_tipo_asentamiento":"27","clave_municipio":"7","identificador_asentamiento":"5349","zona_asentamiento":"Rural","clave_interna_cp_ciudad":""},{"id":"88581","codigo_postal_asentamiento":"67954","nombre_asentamiento":"El Sauz","tipo_asentamiento":"Poblado comunal","nombre_municipio":"Aramberri","nombre_estado":"Nuevo Le\u00f3n","nombre_ciudad":"","codigo_postal_oficina":"67851","clave_estado":"19","codigo_postal_oficina_":"67851","c_cp_vacio":"","clave_tipo_asentamiento":"27","clave_municipio":"7","identificador_asentamiento":"5289","zona_asentamiento":"Rural","clave_interna_cp_ciudad":""},{"id":"88582","codigo_postal_asentamiento":"67955","nombre_asentamiento":"La Caballada","tipo_asentamiento":"Ejido","nombre_municipio":"Aramberri","nombre_estado":"Nuevo Le\u00f3n","nombre_ciudad":"","codigo_postal_oficina":"67901","clave_estado":"19","codigo_postal_oficina_":"67901","c_cp_vacio":"","clave_tipo_asentamiento":"15","clave_municipio":"7","identificador_asentamiento":"2413","zona_asentamiento":"Rural","clave_interna_cp_ciudad":""},{"id":"88583","codigo_postal_asentamiento":"67955","nombre_asentamiento":"San Jose Del Jilguero","tipo_asentamiento":"Ejido","nombre_municipio":"Aramberri","nombre_estado":"Nuevo Le\u00f3n","nombre_ciudad":"","codigo_postal_oficina":"67901","clave_estado":"19","codigo_postal_oficina_":"67901","c_cp_vacio":"","clave_tipo_asentamiento":"15","clave_municipio":"7","identificador_asentamiento":"2415","zona_asentamiento":"Rural","clave_interna_cp_ciudad":""},{"id":"88584","codigo_postal_asentamiento":"67955","nombre_asentamiento":"Puerto Bajo","tipo_asentamiento":"Poblado comunal","nombre_municipio":"Aramberri","nombre_estado":"Nuevo Le\u00f3n","nombre_ciudad":"","codigo_postal_oficina":"67901","clave_estado":"19","codigo_postal_oficina_":"67901","c_cp_vacio":"","clave_tipo_asentamiento":"27","clave_municipio":"7","identificador_asentamiento":"5369","zona_asentamiento":"Rural","clave_interna_cp_ciudad":""},{"id":"88585","codigo_postal_asentamiento":"67955","nombre_asentamiento":"Milpillas","tipo_asentamiento":"Ejido","nombre_municipio":"Aramberri","nombre_estado":"Nuevo Le\u00f3n","nombre_ciudad":"","codigo_postal_oficina":"67901","clave_estado":"19","codigo_postal_oficina_":"67901","c_cp_vacio":"","clave_tipo_asentamiento":"15","clave_municipio":"7","identificador_asentamiento":"2414","zona_asentamiento":"Rural","clave_interna_cp_ciudad":""},{"id":"88586","codigo_postal_asentamiento":"67955","nombre_asentamiento":"Guadalupe de los Navarro","tipo_asentamiento":"Poblado comunal","nombre_municipio":"Aramberri","nombre_estado":"Nuevo Le\u00f3n","nombre_ciudad":"","codigo_postal_oficina":"67901","clave_estado":"19","codigo_postal_oficina_":"67901","c_cp_vacio":"","clave_tipo_asentamiento":"27","clave_municipio":"7","identificador_asentamiento":"5301","zona_asentamiento":"Rural","clave_interna_cp_ciudad":""},{"id":"88587","codigo_postal_asentamiento":"67955","nombre_asentamiento":"Juan M\u00e9ndez Castro","tipo_asentamiento":"Poblado comunal","nombre_municipio":"Aramberri","nombre_estado":"Nuevo Le\u00f3n","nombre_ciudad":"","codigo_postal_oficina":"67901","clave_estado":"19","codigo_postal_oficina_":"67901","c_cp_vacio":"","clave_tipo_asentamiento":"27","clave_municipio":"7","identificador_asentamiento":"5307","zona_asentamiento":"Rural","clave_interna_cp_ciudad":""},{"id":"88588","codigo_postal_asentamiento":"67955","nombre_asentamiento":"La Atarjea (El Pinal)","tipo_asentamiento":"Poblado comunal","nombre_municipio":"Aramberri","nombre_estado":"Nuevo Le\u00f3n","nombre_ciudad":"","codigo_postal_oficina":"67901","clave_estado":"19","codigo_postal_oficina_":"67901","c_cp_vacio":"","clave_tipo_asentamiento":"27","clave_municipio":"7","identificador_asentamiento":"5310","zona_asentamiento":"Rural","clave_interna_cp_ciudad":""},{"id":"88589","codigo_postal_asentamiento":"67955","nombre_asentamiento":"La Canoa","tipo_asentamiento":"Poblado comunal","nombre_municipio":"Aramberri","nombre_estado":"Nuevo Le\u00f3n","nombre_ciudad":"","codigo_postal_oficina":"67901","clave_estado":"19","codigo_postal_oficina_":"67901","c_cp_vacio":"","clave_tipo_asentamiento":"27","clave_municipio":"7","identificador_asentamiento":"5312","zona_asentamiento":"Rural","clave_interna_cp_ciudad":""},{"id":"88590","codigo_postal_asentamiento":"67955","nombre_asentamiento":"La Colorada","tipo_asentamiento":"Poblado comunal","nombre_municipio":"Aramberri","nombre_estado":"Nuevo Le\u00f3n","nombre_ciudad":"","codigo_postal_oficina":"67901","clave_estado":"19","codigo_postal_oficina_":"67901","c_cp_vacio":"","clave_tipo_asentamiento":"27","clave_municipio":"7","identificador_asentamiento":"5314","zona_asentamiento":"Rural","clave_interna_cp_ciudad":""},{"id":"88591","codigo_postal_asentamiento":"67955","nombre_asentamiento":"La Mesa de Alcocer","tipo_asentamiento":"Poblado comunal","nombre_municipio":"Aramberri","nombre_estado":"Nuevo Le\u00f3n","nombre_ciudad":"","codigo_postal_oficina":"67901","clave_estado":"19","codigo_postal_oficina_":"67901","c_cp_vacio":"","clave_tipo_asentamiento":"27","clave_municipio":"7","identificador_asentamiento":"5323","zona_asentamiento":"Rural","clave_interna_cp_ciudad":""},{"id":"88592","codigo_postal_asentamiento":"67955","nombre_asentamiento":"Vista Hermosa","tipo_asentamiento":"Poblado comunal","nombre_municipio":"Aramberri","nombre_estado":"Nuevo Le\u00f3n","nombre_ciudad":"","codigo_postal_oficina":"67901","clave_estado":"19","codigo_postal_oficina_":"67901","c_cp_vacio":"","clave_tipo_asentamiento":"27","clave_municipio":"7","identificador_asentamiento":"5393","zona_asentamiento":"Rural","clave_interna_cp_ciudad":""},{"id":"88593","codigo_postal_asentamiento":"67955","nombre_asentamiento":"El Jilguero","tipo_asentamiento":"Poblado comunal","nombre_municipio":"Aramberri","nombre_estado":"Nuevo Le\u00f3n","nombre_ciudad":"","codigo_postal_oficina":"67901","clave_estado":"19","codigo_postal_oficina_":"67901","c_cp_vacio":"","clave_tipo_asentamiento":"27","clave_municipio":"7","identificador_asentamiento":"5262","zona_asentamiento":"Rural","clave_interna_cp_ciudad":""},{"id":"88594","codigo_postal_asentamiento":"67955","nombre_asentamiento":"La Angostura","tipo_asentamiento":"Poblado comunal","nombre_municipio":"Aramberri","nombre_estado":"Nuevo Le\u00f3n","nombre_ciudad":"","codigo_postal_oficina":"67901","clave_estado":"19","codigo_postal_oficina_":"67901","c_cp_vacio":"","clave_tipo_asentamiento":"27","clave_municipio":"7","identificador_asentamiento":"5308","zona_asentamiento":"Rural","clave_interna_cp_ciudad":""},{"id":"88595","codigo_postal_asentamiento":"67955","nombre_asentamiento":"Agua de Enmedio (Los Pocitos)","tipo_asentamiento":"Poblado comunal","nombre_municipio":"Aramberri","nombre_estado":"Nuevo Le\u00f3n","nombre_ciudad":"","codigo_postal_oficina":"67901","clave_estado":"19","codigo_postal_oficina_":"67901","c_cp_vacio":"","clave_tipo_asentamiento":"27","clave_municipio":"7","identificador_asentamiento":"5233","zona_asentamiento":"Rural","clave_interna_cp_ciudad":""},{"id":"88596","codigo_postal_asentamiento":"67955","nombre_asentamiento":"Guadalupe Victoria","tipo_asentamiento":"Poblado comunal","nombre_municipio":"Aramberri","nombre_estado":"Nuevo Le\u00f3n","nombre_ciudad":"","codigo_postal_oficina":"67901","clave_estado":"19","codigo_postal_oficina_":"67901","c_cp_vacio":"","clave_tipo_asentamiento":"27","clave_municipio":"7","identificador_asentamiento":"5302","zona_asentamiento":"Rural","clave_interna_cp_ciudad":""},{"id":"88597","codigo_postal_asentamiento":"67955","nombre_asentamiento":"La Muralla","tipo_asentamiento":"Poblado comunal","nombre_municipio":"Aramberri","nombre_estado":"Nuevo Le\u00f3n","nombre_ciudad":"","codigo_postal_oficina":"67901","clave_estado":"19","codigo_postal_oficina_":"67901","c_cp_vacio":"","clave_tipo_asentamiento":"27","clave_municipio":"7","identificador_asentamiento":"5324","zona_asentamiento":"Rural","clave_interna_cp_ciudad":""},{"id":"88598","codigo_postal_asentamiento":"67955","nombre_asentamiento":"San Rafael de la Angostura (La Cueva)","tipo_asentamiento":"Poblado comunal","nombre_municipio":"Aramberri","nombre_estado":"Nuevo Le\u00f3n","nombre_ciudad":"","codigo_postal_oficina":"67901","clave_estado":"19","codigo_postal_oficina_":"67901","c_cp_vacio":"","clave_tipo_asentamiento":"27","clave_municipio":"7","identificador_asentamiento":"5385","zona_asentamiento":"Rural","clave_interna_cp_ciudad":""},{"id":"88599","codigo_postal_asentamiento":"67955","nombre_asentamiento":"El Rocio","tipo_asentamiento":"Poblado comunal","nombre_municipio":"Aramberri","nombre_estado":"Nuevo Le\u00f3n","nombre_ciudad":"","codigo_postal_oficina":"67901","clave_estado":"19","codigo_postal_oficina_":"67901","c_cp_vacio":"","clave_tipo_asentamiento":"27","clave_municipio":"7","identificador_asentamiento":"5287","zona_asentamiento":"Rural","clave_interna_cp_ciudad":""},{"id":"88600","codigo_postal_asentamiento":"67956","nombre_asentamiento":"Presa de las Animas","tipo_asentamiento":"Hacienda","nombre_municipio":"Aramberri","nombre_estado":"Nuevo Le\u00f3n","nombre_ciudad":"","codigo_postal_oficina":"67901","clave_estado":"19","codigo_postal_oficina_":"67901","c_cp_vacio":"","clave_tipo_asentamiento":"24","clave_municipio":"7","identificador_asentamiento":"2417","zona_asentamiento":"Rural","clave_interna_cp_ciudad":""},{"id":"88601","codigo_postal_asentamiento":"67956","nombre_asentamiento":"Puerto Pi\u00f1ones","tipo_asentamiento":"Poblado comunal","nombre_municipio":"Aramberri","nombre_estado":"Nuevo Le\u00f3n","nombre_ciudad":"","codigo_postal_oficina":"67901","clave_estado":"19","codigo_postal_oficina_":"67901","c_cp_vacio":"","clave_tipo_asentamiento":"27","clave_municipio":"7","identificador_asentamiento":"5372","zona_asentamiento":"Rural","clave_interna_cp_ciudad":""},{"id":"88602","codigo_postal_asentamiento":"67956","nombre_asentamiento":"La Majada","tipo_asentamiento":"Poblado comunal","nombre_municipio":"Aramberri","nombre_estado":"Nuevo Le\u00f3n","nombre_ciudad":"","codigo_postal_oficina":"67901","clave_estado":"19","codigo_postal_oficina_":"67901","c_cp_vacio":"","clave_tipo_asentamiento":"27","clave_municipio":"7","identificador_asentamiento":"5322","zona_asentamiento":"Rural","clave_interna_cp_ciudad":""},{"id":"88603","codigo_postal_asentamiento":"67956","nombre_asentamiento":"Rancho Nuevo","tipo_asentamiento":"Rancher\u00eda","nombre_municipio":"Aramberri","nombre_estado":"Nuevo Le\u00f3n","nombre_ciudad":"","codigo_postal_oficina":"67901","clave_estado":"19","codigo_postal_oficina_":"67901","c_cp_vacio":"","clave_tipo_asentamiento":"29","clave_municipio":"7","identificador_asentamiento":"5375","zona_asentamiento":"Rural","clave_interna_cp_ciudad":""},{"id":"88604","codigo_postal_asentamiento":"67956","nombre_asentamiento":"San Enrique (Los Mendoza)","tipo_asentamiento":"Poblado comunal","nombre_municipio":"Aramberri","nombre_estado":"Nuevo Le\u00f3n","nombre_ciudad":"","codigo_postal_oficina":"67901","clave_estado":"19","codigo_postal_oficina_":"67901","c_cp_vacio":"","clave_tipo_asentamiento":"27","clave_municipio":"7","identificador_asentamiento":"5380","zona_asentamiento":"Rural","clave_interna_cp_ciudad":""},{"id":"88605","codigo_postal_asentamiento":"67956","nombre_asentamiento":"San Juanito de Sol\u00eds","tipo_asentamiento":"Ejido","nombre_municipio":"Aramberri","nombre_estado":"Nuevo Le\u00f3n","nombre_ciudad":"","codigo_postal_oficina":"67901","clave_estado":"19","codigo_postal_oficina_":"67901","c_cp_vacio":"","clave_tipo_asentamiento":"15","clave_municipio":"7","identificador_asentamiento":"2411","zona_asentamiento":"Rural","clave_interna_cp_ciudad":""},{"id":"88606","codigo_postal_asentamiento":"67956","nombre_asentamiento":"San Isidro","tipo_asentamiento":"Ejido","nombre_municipio":"Aramberri","nombre_estado":"Nuevo Le\u00f3n","nombre_ciudad":"","codigo_postal_oficina":"67901","clave_estado":"19","codigo_postal_oficina_":"67901","c_cp_vacio":"","clave_tipo_asentamiento":"15","clave_municipio":"7","identificador_asentamiento":"2418","zona_asentamiento":"Rural","clave_interna_cp_ciudad":""},{"id":"88607","codigo_postal_asentamiento":"67956","nombre_asentamiento":"Centro Caprino","tipo_asentamiento":"Poblado comunal","nombre_municipio":"Aramberri","nombre_estado":"Nuevo Le\u00f3n","nombre_ciudad":"","codigo_postal_oficina":"67901","clave_estado":"19","codigo_postal_oficina_":"67901","c_cp_vacio":"","clave_tipo_asentamiento":"27","clave_municipio":"7","identificador_asentamiento":"5243","zona_asentamiento":"Rural","clave_interna_cp_ciudad":""},{"id":"88608","codigo_postal_asentamiento":"67956","nombre_asentamiento":"Las Juanas","tipo_asentamiento":"Poblado comunal","nombre_municipio":"Aramberri","nombre_estado":"Nuevo Le\u00f3n","nombre_ciudad":"","codigo_postal_oficina":"67901","clave_estado":"19","codigo_postal_oficina_":"67901","c_cp_vacio":"","clave_tipo_asentamiento":"27","clave_municipio":"7","identificador_asentamiento":"5345","zona_asentamiento":"Rural","clave_interna_cp_ciudad":""},{"id":"88609","codigo_postal_asentamiento":"67957","nombre_asentamiento":"El Para\u00edso (San Antonio Mesa de las Piedras)","tipo_asentamiento":"Poblado comunal","nombre_municipio":"Aramberri","nombre_estado":"Nuevo Le\u00f3n","nombre_ciudad":"","codigo_postal_oficina":"67901","clave_estado":"19","codigo_postal_oficina_":"67901","c_cp_vacio":"","clave_tipo_asentamiento":"27","clave_municipio":"7","identificador_asentamiento":"5272","zona_asentamiento":"Rural","clave_interna_cp_ciudad":""},{"id":"88610","codigo_postal_asentamiento":"67957","nombre_asentamiento":"El Yerbaniz","tipo_asentamiento":"Poblado comunal","nombre_municipio":"Aramberri","nombre_estado":"Nuevo Le\u00f3n","nombre_ciudad":"","codigo_postal_oficina":"67901","clave_estado":"19","codigo_postal_oficina_":"67901","c_cp_vacio":"","clave_tipo_asentamiento":"27","clave_municipio":"7","identificador_asentamiento":"5295","zona_asentamiento":"Rural","clave_interna_cp_ciudad":""},{"id":"88611","codigo_postal_asentamiento":"67957","nombre_asentamiento":"La Boquilla","tipo_asentamiento":"Poblado comunal","nombre_municipio":"Aramberri","nombre_estado":"Nuevo Le\u00f3n","nombre_ciudad":"","codigo_postal_oficina":"67901","clave_estado":"19","codigo_postal_oficina_":"67901","c_cp_vacio":"","clave_tipo_asentamiento":"27","clave_municipio":"7","identificador_asentamiento":"5311","zona_asentamiento":"Rural","clave_interna_cp_ciudad":""},{"id":"88612","codigo_postal_asentamiento":"67957","nombre_asentamiento":"El Jard\u00edn (Ca\u00f1\u00f3n de Vacas)","tipo_asentamiento":"Poblado comunal","nombre_municipio":"Aramberri","nombre_estado":"Nuevo Le\u00f3n","nombre_ciudad":"","codigo_postal_oficina":"67901","clave_estado":"19","codigo_postal_oficina_":"67901","c_cp_vacio":"","clave_tipo_asentamiento":"27","clave_municipio":"7","identificador_asentamiento":"5261","zona_asentamiento":"Rural","clave_interna_cp_ciudad":""},{"id":"88613","codigo_postal_asentamiento":"67957","nombre_asentamiento":"El Saucillo","tipo_asentamiento":"Poblado comunal","nombre_municipio":"Aramberri","nombre_estado":"Nuevo Le\u00f3n","nombre_ciudad":"","codigo_postal_oficina":"67901","clave_estado":"19","codigo_postal_oficina_":"67901","c_cp_vacio":"","clave_tipo_asentamiento":"27","clave_municipio":"7","identificador_asentamiento":"5288","zona_asentamiento":"Rural","clave_interna_cp_ciudad":""},{"id":"88614","codigo_postal_asentamiento":"67957","nombre_asentamiento":"La Reforma","tipo_asentamiento":"Poblado comunal","nombre_municipio":"Aramberri","nombre_estado":"Nuevo Le\u00f3n","nombre_ciudad":"","codigo_postal_oficina":"67901","clave_estado":"19","codigo_postal_oficina_":"67901","c_cp_vacio":"","clave_tipo_asentamiento":"27","clave_municipio":"7","identificador_asentamiento":"5331","zona_asentamiento":"Rural","clave_interna_cp_ciudad":""},{"id":"88615","codigo_postal_asentamiento":"67957","nombre_asentamiento":"San Francisco de Leos","tipo_asentamiento":"Poblado comunal","nombre_municipio":"Aramberri","nombre_estado":"Nuevo Le\u00f3n","nombre_ciudad":"","codigo_postal_oficina":"67901","clave_estado":"19","codigo_postal_oficina_":"67901","c_cp_vacio":"","clave_tipo_asentamiento":"27","clave_municipio":"7","identificador_asentamiento":"5381","zona_asentamiento":"Rural","clave_interna_cp_ciudad":""},{"id":"88616","codigo_postal_asentamiento":"67957","nombre_asentamiento":"El Leoncito","tipo_asentamiento":"Poblado comunal","nombre_municipio":"Aramberri","nombre_estado":"Nuevo Le\u00f3n","nombre_ciudad":"","codigo_postal_oficina":"67901","clave_estado":"19","codigo_postal_oficina_":"67901","c_cp_vacio":"","clave_tipo_asentamiento":"27","clave_municipio":"7","identificador_asentamiento":"5263","zona_asentamiento":"Rural","clave_interna_cp_ciudad":""},{"id":"88617","codigo_postal_asentamiento":"67957","nombre_asentamiento":"Las Palmas","tipo_asentamiento":"Poblado comunal","nombre_municipio":"Aramberri","nombre_estado":"Nuevo Le\u00f3n","nombre_ciudad":"","codigo_postal_oficina":"67901","clave_estado":"19","codigo_postal_oficina_":"67901","c_cp_vacio":"","clave_tipo_asentamiento":"27","clave_municipio":"7","identificador_asentamiento":"5348","zona_asentamiento":"Rural","clave_interna_cp_ciudad":""},{"id":"88618","codigo_postal_asentamiento":"67957","nombre_asentamiento":"El Cuervo Uno","tipo_asentamiento":"Poblado comunal","nombre_municipio":"Aramberri","nombre_estado":"Nuevo Le\u00f3n","nombre_ciudad":"","codigo_postal_oficina":"67901","clave_estado":"19","codigo_postal_oficina_":"67901","c_cp_vacio":"","clave_tipo_asentamiento":"27","clave_municipio":"7","identificador_asentamiento":"5257","zona_asentamiento":"Rural","clave_interna_cp_ciudad":""},{"id":"88619","codigo_postal_asentamiento":"67957","nombre_asentamiento":"El Rodeo","tipo_asentamiento":"Poblado comunal","nombre_municipio":"Aramberri","nombre_estado":"Nuevo Le\u00f3n","nombre_ciudad":"","codigo_postal_oficina":"67901","clave_estado":"19","codigo_postal_oficina_":"67901","c_cp_vacio":"","clave_tipo_asentamiento":"27","clave_municipio":"7","identificador_asentamiento":"5285","zona_asentamiento":"Rural","clave_interna_cp_ciudad":""},{"id":"88620","codigo_postal_asentamiento":"67957","nombre_asentamiento":"Hoya de Bocacil","tipo_asentamiento":"Poblado comunal","nombre_municipio":"Aramberri","nombre_estado":"Nuevo Le\u00f3n","nombre_ciudad":"","codigo_postal_oficina":"67901","clave_estado":"19","codigo_postal_oficina_":"67901","c_cp_vacio":"","clave_tipo_asentamiento":"27","clave_municipio":"7","identificador_asentamiento":"5303","zona_asentamiento":"Rural","clave_interna_cp_ciudad":""},{"id":"88621","codigo_postal_asentamiento":"67957","nombre_asentamiento":"El Cuervo Dos","tipo_asentamiento":"Poblado comunal","nombre_municipio":"Aramberri","nombre_estado":"Nuevo Le\u00f3n","nombre_ciudad":"","codigo_postal_oficina":"67901","clave_estado":"19","codigo_postal_oficina_":"67901","c_cp_vacio":"","clave_tipo_asentamiento":"27","clave_municipio":"7","identificador_asentamiento":"5256","zona_asentamiento":"Rural","clave_interna_cp_ciudad":""},{"id":"88622","codigo_postal_asentamiento":"67957","nombre_asentamiento":"El Nacimiento","tipo_asentamiento":"Poblado comunal","nombre_municipio":"Aramberri","nombre_estado":"Nuevo Le\u00f3n","nombre_ciudad":"","codigo_postal_oficina":"67901","clave_estado":"19","codigo_postal_oficina_":"67901","c_cp_vacio":"","clave_tipo_asentamiento":"27","clave_municipio":"7","identificador_asentamiento":"5268","zona_asentamiento":"Rural","clave_interna_cp_ciudad":""},{"id":"88623","codigo_postal_asentamiento":"67957","nombre_asentamiento":"El Refugio (Refugio de Texas)","tipo_asentamiento":"Poblado comunal","nombre_municipio":"Aramberri","nombre_estado":"Nuevo Le\u00f3n","nombre_ciudad":"","codigo_postal_oficina":"67901","clave_estado":"19","codigo_postal_oficina_":"67901","c_cp_vacio":"","clave_tipo_asentamiento":"27","clave_municipio":"7","identificador_asentamiento":"5282","zona_asentamiento":"Rural","clave_interna_cp_ciudad":""},{"id":"88624","codigo_postal_asentamiento":"67957","nombre_asentamiento":"San Antonio","tipo_asentamiento":"Poblado comunal","nombre_municipio":"Aramberri","nombre_estado":"Nuevo Le\u00f3n","nombre_ciudad":"","codigo_postal_oficina":"67901","clave_estado":"19","codigo_postal_oficina_":"67901","c_cp_vacio":"","clave_tipo_asentamiento":"27","clave_municipio":"7","identificador_asentamiento":"5379","zona_asentamiento":"Rural","clave_interna_cp_ciudad":""},{"id":"88625","codigo_postal_asentamiento":"67957","nombre_asentamiento":"Lampacitos","tipo_asentamiento":"Ejido","nombre_municipio":"Aramberri","nombre_estado":"Nuevo Le\u00f3n","nombre_ciudad":"","codigo_postal_oficina":"67901","clave_estado":"19","codigo_postal_oficina_":"67901","c_cp_vacio":"","clave_tipo_asentamiento":"15","clave_municipio":"7","identificador_asentamiento":"2400","zona_asentamiento":"Rural","clave_interna_cp_ciudad":""},{"id":"88626","codigo_postal_asentamiento":"67957","nombre_asentamiento":"La Corona","tipo_asentamiento":"Poblado comunal","nombre_municipio":"Aramberri","nombre_estado":"Nuevo Le\u00f3n","nombre_ciudad":"","codigo_postal_oficina":"67901","clave_estado":"19","codigo_postal_oficina_":"67901","c_cp_vacio":"","clave_tipo_asentamiento":"27","clave_municipio":"7","identificador_asentamiento":"5315","zona_asentamiento":"Rural","clave_interna_cp_ciudad":""},{"id":"88627","codigo_postal_asentamiento":"67957","nombre_asentamiento":"Las Higueritas","tipo_asentamiento":"Poblado comunal","nombre_municipio":"Aramberri","nombre_estado":"Nuevo Le\u00f3n","nombre_ciudad":"","codigo_postal_oficina":"67901","clave_estado":"19","codigo_postal_oficina_":"67901","c_cp_vacio":"","clave_tipo_asentamiento":"27","clave_municipio":"7","identificador_asentamiento":"5343","zona_asentamiento":"Rural","clave_interna_cp_ciudad":""},{"id":"88628","codigo_postal_asentamiento":"67957","nombre_asentamiento":"Yerbaniz","tipo_asentamiento":"Poblado comunal","nombre_municipio":"Aramberri","nombre_estado":"Nuevo Le\u00f3n","nombre_ciudad":"","codigo_postal_oficina":"67901","clave_estado":"19","codigo_postal_oficina_":"67901","c_cp_vacio":"","clave_tipo_asentamiento":"27","clave_municipio":"7","identificador_asentamiento":"5394","zona_asentamiento":"Rural","clave_interna_cp_ciudad":""},{"id":"88629","codigo_postal_asentamiento":"67957","nombre_asentamiento":"El Astillero","tipo_asentamiento":"Poblado comunal","nombre_municipio":"Aramberri","nombre_estado":"Nuevo Le\u00f3n","nombre_ciudad":"","codigo_postal_oficina":"67901","clave_estado":"19","codigo_postal_oficina_":"67901","c_cp_vacio":"","clave_tipo_asentamiento":"27","clave_municipio":"7","identificador_asentamiento":"5250","zona_asentamiento":"Rural","clave_interna_cp_ciudad":""},{"id":"88630","codigo_postal_asentamiento":"67957","nombre_asentamiento":"Las Delicias","tipo_asentamiento":"Poblado comunal","nombre_municipio":"Aramberri","nombre_estado":"Nuevo Le\u00f3n","nombre_ciudad":"","codigo_postal_oficina":"67901","clave_estado":"19","codigo_postal_oficina_":"67901","c_cp_vacio":"","clave_tipo_asentamiento":"27","clave_municipio":"7","identificador_asentamiento":"5341","zona_asentamiento":"Rural","clave_interna_cp_ciudad":""},{"id":"88631","codigo_postal_asentamiento":"67957","nombre_asentamiento":"Ca\u00f1\u00f3n de Vacas (El Jard\u00edn)","tipo_asentamiento":"Poblado comunal","nombre_municipio":"Aramberri","nombre_estado":"Nuevo Le\u00f3n","nombre_ciudad":"","codigo_postal_oficina":"67901","clave_estado":"19","codigo_postal_oficina_":"67901","c_cp_vacio":"","clave_tipo_asentamiento":"27","clave_municipio":"7","identificador_asentamiento":"5240","zona_asentamiento":"Rural","clave_interna_cp_ciudad":""},{"id":"88632","codigo_postal_asentamiento":"67957","nombre_asentamiento":"Las Joyitas","tipo_asentamiento":"Poblado comunal","nombre_municipio":"Aramberri","nombre_estado":"Nuevo Le\u00f3n","nombre_ciudad":"","codigo_postal_oficina":"67901","clave_estado":"19","codigo_postal_oficina_":"67901","c_cp_vacio":"","clave_tipo_asentamiento":"27","clave_municipio":"7","identificador_asentamiento":"5344","zona_asentamiento":"Rural","clave_interna_cp_ciudad":""},{"id":"88633","codigo_postal_asentamiento":"67958","nombre_asentamiento":"Ibarrilla (Rinc\u00f3n de Ibarrilla)","tipo_asentamiento":"Congregaci\u00f3n","nombre_municipio":"Aramberri","nombre_estado":"Nuevo Le\u00f3n","nombre_ciudad":"","codigo_postal_oficina":"67901","clave_estado":"19","codigo_postal_oficina_":"67901","c_cp_vacio":"","clave_tipo_asentamiento":"11","clave_municipio":"7","identificador_asentamiento":"2412","zona_asentamiento":"Rural","clave_interna_cp_ciudad":""},{"id":"88634","codigo_postal_asentamiento":"67958","nombre_asentamiento":"\u00c1lamos","tipo_asentamiento":"Poblado comunal","nombre_municipio":"Aramberri","nombre_estado":"Nuevo Le\u00f3n","nombre_ciudad":"","codigo_postal_oficina":"67901","clave_estado":"19","codigo_postal_oficina_":"67901","c_cp_vacio":"","clave_tipo_asentamiento":"27","clave_municipio":"7","identificador_asentamiento":"5231","zona_asentamiento":"Rural","clave_interna_cp_ciudad":""},{"id":"88635","codigo_postal_asentamiento":"67958","nombre_asentamiento":"Esquivel","tipo_asentamiento":"Poblado comunal","nombre_municipio":"Aramberri","nombre_estado":"Nuevo Le\u00f3n","nombre_ciudad":"","codigo_postal_oficina":"67901","clave_estado":"19","codigo_postal_oficina_":"67901","c_cp_vacio":"","clave_tipo_asentamiento":"27","clave_municipio":"7","identificador_asentamiento":"5297","zona_asentamiento":"Rural","clave_interna_cp_ciudad":""},{"id":"88636","codigo_postal_asentamiento":"67958","nombre_asentamiento":"Ignacio Zaragoza","tipo_asentamiento":"Poblado comunal","nombre_municipio":"Aramberri","nombre_estado":"Nuevo Le\u00f3n","nombre_ciudad":"","codigo_postal_oficina":"67901","clave_estado":"19","codigo_postal_oficina_":"67901","c_cp_vacio":"","clave_tipo_asentamiento":"27","clave_municipio":"7","identificador_asentamiento":"5304","zona_asentamiento":"Rural","clave_interna_cp_ciudad":""},{"id":"88637","codigo_postal_asentamiento":"67958","nombre_asentamiento":"Ojo de Agua","tipo_asentamiento":"Rancher\u00eda","nombre_municipio":"Aramberri","nombre_estado":"Nuevo Le\u00f3n","nombre_ciudad":"","codigo_postal_oficina":"67901","clave_estado":"19","codigo_postal_oficina_":"67901","c_cp_vacio":"","clave_tipo_asentamiento":"29","clave_municipio":"7","identificador_asentamiento":"5362","zona_asentamiento":"Rural","clave_interna_cp_ciudad":""},{"id":"88638","codigo_postal_asentamiento":"67958","nombre_asentamiento":"Duraznillos","tipo_asentamiento":"Poblado comunal","nombre_municipio":"Aramberri","nombre_estado":"Nuevo Le\u00f3n","nombre_ciudad":"","codigo_postal_oficina":"67901","clave_estado":"19","codigo_postal_oficina_":"67901","c_cp_vacio":"","clave_tipo_asentamiento":"27","clave_municipio":"7","identificador_asentamiento":"5247","zona_asentamiento":"Rural","clave_interna_cp_ciudad":""},{"id":"88639","codigo_postal_asentamiento":"67958","nombre_asentamiento":"El Naranjo","tipo_asentamiento":"Poblado comunal","nombre_municipio":"Aramberri","nombre_estado":"Nuevo Le\u00f3n","nombre_ciudad":"","codigo_postal_oficina":"67901","clave_estado":"19","codigo_postal_oficina_":"67901","c_cp_vacio":"","clave_tipo_asentamiento":"27","clave_municipio":"7","identificador_asentamiento":"5269","zona_asentamiento":"Rural","clave_interna_cp_ciudad":""},{"id":"88640","codigo_postal_asentamiento":"67958","nombre_asentamiento":"El Puerto","tipo_asentamiento":"Poblado comunal","nombre_municipio":"Aramberri","nombre_estado":"Nuevo Le\u00f3n","nombre_ciudad":"","codigo_postal_oficina":"67901","clave_estado":"19","codigo_postal_oficina_":"67901","c_cp_vacio":"","clave_tipo_asentamiento":"27","clave_municipio":"7","identificador_asentamiento":"5277","zona_asentamiento":"Rural","clave_interna_cp_ciudad":""},{"id":"88641","codigo_postal_asentamiento":"67958","nombre_asentamiento":"La Tinaja","tipo_asentamiento":"Poblado comunal","nombre_municipio":"Aramberri","nombre_estado":"Nuevo Le\u00f3n","nombre_ciudad":"","codigo_postal_oficina":"67901","clave_estado":"19","codigo_postal_oficina_":"67901","c_cp_vacio":"","clave_tipo_asentamiento":"27","clave_municipio":"7","identificador_asentamiento":"5335","zona_asentamiento":"Rural","clave_interna_cp_ciudad":""},{"id":"88642","codigo_postal_asentamiento":"67958","nombre_asentamiento":"Ballenitas","tipo_asentamiento":"Poblado comunal","nombre_municipio":"Aramberri","nombre_estado":"Nuevo Le\u00f3n","nombre_ciudad":"","codigo_postal_oficina":"67901","clave_estado":"19","codigo_postal_oficina_":"67901","c_cp_vacio":"","clave_tipo_asentamiento":"27","clave_municipio":"7","identificador_asentamiento":"5239","zona_asentamiento":"Rural","clave_interna_cp_ciudad":""},{"id":"88643","codigo_postal_asentamiento":"67958","nombre_asentamiento":"Puerto Rinc\u00f3n de Jes\u00fas","tipo_asentamiento":"Poblado comunal","nombre_municipio":"Aramberri","nombre_estado":"Nuevo Le\u00f3n","nombre_ciudad":"","codigo_postal_oficina":"67901","clave_estado":"19","codigo_postal_oficina_":"67901","c_cp_vacio":"","clave_tipo_asentamiento":"27","clave_municipio":"7","identificador_asentamiento":"5373","zona_asentamiento":"Rural","clave_interna_cp_ciudad":""},{"id":"88644","codigo_postal_asentamiento":"67958","nombre_asentamiento":"El Divisadero","tipo_asentamiento":"Poblado comunal","nombre_municipio":"Aramberri","nombre_estado":"Nuevo Le\u00f3n","nombre_ciudad":"","codigo_postal_oficina":"67901","clave_estado":"19","codigo_postal_oficina_":"67901","c_cp_vacio":"","clave_tipo_asentamiento":"27","clave_municipio":"7","identificador_asentamiento":"5259","zona_asentamiento":"Rural","clave_interna_cp_ciudad":""},{"id":"88645","codigo_postal_asentamiento":"67958","nombre_asentamiento":"El Rinc\u00f3n de Jes\u00fas","tipo_asentamiento":"Poblado comunal","nombre_municipio":"Aramberri","nombre_estado":"Nuevo Le\u00f3n","nombre_ciudad":"","codigo_postal_oficina":"67901","clave_estado":"19","codigo_postal_oficina_":"67901","c_cp_vacio":"","clave_tipo_asentamiento":"27","clave_municipio":"7","identificador_asentamiento":"5284","zona_asentamiento":"Rural","clave_interna_cp_ciudad":""},{"id":"88646","codigo_postal_asentamiento":"67958","nombre_asentamiento":"El Sauz","tipo_asentamiento":"Poblado comunal","nombre_municipio":"Aramberri","nombre_estado":"Nuevo Le\u00f3n","nombre_ciudad":"","codigo_postal_oficina":"67901","clave_estado":"19","codigo_postal_oficina_":"67901","c_cp_vacio":"","clave_tipo_asentamiento":"27","clave_municipio":"7","identificador_asentamiento":"5290","zona_asentamiento":"Rural","clave_interna_cp_ciudad":""},{"id":"88647","codigo_postal_asentamiento":"67958","nombre_asentamiento":"Lagunitas","tipo_asentamiento":"Poblado comunal","nombre_municipio":"Aramberri","nombre_estado":"Nuevo Le\u00f3n","nombre_ciudad":"","codigo_postal_oficina":"67901","clave_estado":"19","codigo_postal_oficina_":"67901","c_cp_vacio":"","clave_tipo_asentamiento":"27","clave_municipio":"7","identificador_asentamiento":"5340","zona_asentamiento":"Rural","clave_interna_cp_ciudad":""},{"id":"88648","codigo_postal_asentamiento":"67958","nombre_asentamiento":"Los Laureles","tipo_asentamiento":"Poblado comunal","nombre_municipio":"Aramberri","nombre_estado":"Nuevo Le\u00f3n","nombre_ciudad":"","codigo_postal_oficina":"67901","clave_estado":"19","codigo_postal_oficina_":"67901","c_cp_vacio":"","clave_tipo_asentamiento":"27","clave_municipio":"7","identificador_asentamiento":"5353","zona_asentamiento":"Rural","clave_interna_cp_ciudad":""},{"id":"88649","codigo_postal_asentamiento":"67958","nombre_asentamiento":"Ojo de Agua","tipo_asentamiento":"Poblado comunal","nombre_municipio":"Aramberri","nombre_estado":"Nuevo Le\u00f3n","nombre_ciudad":"","codigo_postal_oficina":"67901","clave_estado":"19","codigo_postal_oficina_":"67901","c_cp_vacio":"","clave_tipo_asentamiento":"27","clave_municipio":"7","identificador_asentamiento":"5359","zona_asentamiento":"Rural","clave_interna_cp_ciudad":""},{"id":"88650","codigo_postal_asentamiento":"67958","nombre_asentamiento":"El Puerto","tipo_asentamiento":"Rancher\u00eda","nombre_municipio":"Aramberri","nombre_estado":"Nuevo Le\u00f3n","nombre_ciudad":"","codigo_postal_oficina":"67901","clave_estado":"19","codigo_postal_oficina_":"67901","c_cp_vacio":"","clave_tipo_asentamiento":"29","clave_municipio":"7","identificador_asentamiento":"5279","zona_asentamiento":"Rural","clave_interna_cp_ciudad":""},{"id":"88651","codigo_postal_asentamiento":"67958","nombre_asentamiento":"Las Mulas","tipo_asentamiento":"Poblado comunal","nombre_municipio":"Aramberri","nombre_estado":"Nuevo Le\u00f3n","nombre_ciudad":"","codigo_postal_oficina":"67901","clave_estado":"19","codigo_postal_oficina_":"67901","c_cp_vacio":"","clave_tipo_asentamiento":"27","clave_municipio":"7","identificador_asentamiento":"5347","zona_asentamiento":"Rural","clave_interna_cp_ciudad":""},{"id":"88652","codigo_postal_asentamiento":"67958","nombre_asentamiento":"Monillal","tipo_asentamiento":"Poblado comunal","nombre_municipio":"Aramberri","nombre_estado":"Nuevo Le\u00f3n","nombre_ciudad":"","codigo_postal_oficina":"67901","clave_estado":"19","codigo_postal_oficina_":"67901","c_cp_vacio":"","clave_tipo_asentamiento":"27","clave_municipio":"7","identificador_asentamiento":"5358","zona_asentamiento":"Rural","clave_interna_cp_ciudad":""},{"id":"88653","codigo_postal_asentamiento":"67958","nombre_asentamiento":"La Gata","tipo_asentamiento":"Poblado comunal","nombre_municipio":"Aramberri","nombre_estado":"Nuevo Le\u00f3n","nombre_ciudad":"","codigo_postal_oficina":"67901","clave_estado":"19","codigo_postal_oficina_":"67901","c_cp_vacio":"","clave_tipo_asentamiento":"27","clave_municipio":"7","identificador_asentamiento":"5317","zona_asentamiento":"Rural","clave_interna_cp_ciudad":""},{"id":"88654","codigo_postal_asentamiento":"67959","nombre_asentamiento":"El Tejocote","tipo_asentamiento":"Rancher\u00eda","nombre_municipio":"Aramberri","nombre_estado":"Nuevo Le\u00f3n","nombre_ciudad":"","codigo_postal_oficina":"67901","clave_estado":"19","codigo_postal_oficina_":"67901","c_cp_vacio":"","clave_tipo_asentamiento":"29","clave_municipio":"7","identificador_asentamiento":"2421","zona_asentamiento":"Rural","clave_interna_cp_ciudad":""}]