[{"id":"253043","estado_id":"29","municipio_clave":"8","municipio_id":"2064","clave":"0001","nombre":"Cuapiaxtla","latitud":"191742","longitud":"0974605","altitud":"2448"},{"id":"253044","estado_id":"29","municipio_clave":"8","municipio_id":"2064","clave":"0002","nombre":"La Asunci\u00f3n Rascona","latitud":"191850","longitud":"0974904","altitud":"2451"},{"id":"253045","estado_id":"29","municipio_clave":"8","municipio_id":"2064","clave":"0004","nombre":"Egipto","latitud":"192110","longitud":"0974357","altitud":"2411"},{"id":"253046","estado_id":"29","municipio_clave":"8","municipio_id":"2064","clave":"0005","nombre":"Colonia Ignacio Allende","latitud":"192124","longitud":"0974702","altitud":"2486"},{"id":"253047","estado_id":"29","municipio_clave":"8","municipio_id":"2064","clave":"0006","nombre":"Izocorral","latitud":"192028","longitud":"0974628","altitud":"2489"},{"id":"253048","estado_id":"29","municipio_clave":"8","municipio_id":"2064","clave":"0007","nombre":"Colonia Jos\u00e9 Mar\u00eda Morelos","latitud":"192142","longitud":"0974155","altitud":"2417"},{"id":"253049","estado_id":"29","municipio_clave":"8","municipio_id":"2064","clave":"0010","nombre":"Colonia Manuel \u00c1vila Camacho","latitud":"191933","longitud":"0974460","altitud":"2473"},{"id":"253050","estado_id":"29","municipio_clave":"8","municipio_id":"2064","clave":"0011","nombre":"Plan de Ayala","latitud":"191834","longitud":"0974418","altitud":"2439"},{"id":"253051","estado_id":"29","municipio_clave":"8","municipio_id":"2064","clave":"0012","nombre":"La Providencia","latitud":"192018","longitud":"0974643","altitud":"2472"},{"id":"253052","estado_id":"29","municipio_clave":"8","municipio_id":"2064","clave":"0014","nombre":"San Crist\u00f3bal del R\u00edo","latitud":"192147","longitud":"0974229","altitud":"2400"},{"id":"253053","estado_id":"29","municipio_clave":"8","municipio_id":"2064","clave":"0015","nombre":"Ex-Hacienda San Francisco Cuexcomatepec","latitud":"191938","longitud":"0974245","altitud":"2400"},{"id":"253054","estado_id":"29","municipio_clave":"8","municipio_id":"2064","clave":"0016","nombre":"San Francisco Cuexcontzi","latitud":"191914","longitud":"0974240","altitud":"2420"},{"id":"253055","estado_id":"29","municipio_clave":"8","municipio_id":"2064","clave":"0017","nombre":"San Isidro Cuexcontzi","latitud":"192032","longitud":"0974235","altitud":"2392"},{"id":"253056","estado_id":"29","municipio_clave":"8","municipio_id":"2064","clave":"0019","nombre":"San Felipe Teometitla","latitud":"192006","longitud":"0974630","altitud":"2480"},{"id":"253057","estado_id":"29","municipio_clave":"8","municipio_id":"2064","clave":"0020","nombre":"Rancho Mazarraza","latitud":"191910","longitud":"0974519","altitud":"2448"},{"id":"253058","estado_id":"29","municipio_clave":"8","municipio_id":"2064","clave":"0022","nombre":"San Miguel Teometitla","latitud":"192010","longitud":"0974639","altitud":"2474"},{"id":"253059","estado_id":"29","municipio_clave":"8","municipio_id":"2064","clave":"0023","nombre":"Santa Fe Uno","latitud":"191950","longitud":"0974541","altitud":"2504"},{"id":"253060","estado_id":"29","municipio_clave":"8","municipio_id":"2064","clave":"0025","nombre":"Santa Mar\u00eda Zoapila","latitud":"192028","longitud":"0974549","altitud":"2520"},{"id":"253061","estado_id":"29","municipio_clave":"8","municipio_id":"2064","clave":"0026","nombre":"El Tejocote","latitud":"191903","longitud":"0974441","altitud":"2449"},{"id":"253062","estado_id":"29","municipio_clave":"8","municipio_id":"2064","clave":"0027","nombre":"Colonia Loma Bonita","latitud":"191953","longitud":"0974519","altitud":"2506"},{"id":"253063","estado_id":"29","municipio_clave":"8","municipio_id":"2064","clave":"0028","nombre":"San Rafael Tepatlaxco (Uni\u00f3n y Progreso)","latitud":"192244","longitud":"0975110","altitud":"2574"},{"id":"253064","estado_id":"29","municipio_clave":"8","municipio_id":"2064","clave":"0029","nombre":"Santa Beatriz la Nueva","latitud":"192049","longitud":"0974545","altitud":"2516"},{"id":"253065","estado_id":"29","municipio_clave":"8","municipio_id":"2064","clave":"0031","nombre":"Santa Rebeca","latitud":"191828","longitud":"0974513","altitud":"2429"},{"id":"253066","estado_id":"29","municipio_clave":"8","municipio_id":"2064","clave":"0032","nombre":"San Diego Coyotepec","latitud":"191753","longitud":"0974355","altitud":"2424"},{"id":"253067","estado_id":"29","municipio_clave":"8","municipio_id":"2064","clave":"0033","nombre":"Colonia del Valle","latitud":"191818","longitud":"0974409","altitud":"2435"},{"id":"253068","estado_id":"29","municipio_clave":"8","municipio_id":"2064","clave":"0035","nombre":"Granja de Guadalupe","latitud":"191902","longitud":"0974507","altitud":"2447"},{"id":"253069","estado_id":"29","municipio_clave":"8","municipio_id":"2064","clave":"0036","nombre":"Santa Fe","latitud":"191922","longitud":"0974506","altitud":"2463"},{"id":"253070","estado_id":"29","municipio_clave":"8","municipio_id":"2064","clave":"0049","nombre":"Tecoac [Granja Porcina]","latitud":"192040","longitud":"0974749","altitud":"2460"},{"id":"253071","estado_id":"29","municipio_clave":"8","municipio_id":"2064","clave":"0056","nombre":"Ejido de Allende","latitud":"192231","longitud":"0975052","altitud":"2560"},{"id":"253072","estado_id":"29","municipio_clave":"8","municipio_id":"2064","clave":"0057","nombre":"La Granja (Camino a Franco)","latitud":"192119","longitud":"0974916","altitud":"2460"},{"id":"253073","estado_id":"29","municipio_clave":"8","municipio_id":"2064","clave":"0065","nombre":"Palma de Tres Brazos (Fracci\u00f3n Santo Domingo)","latitud":"192219","longitud":"0975024","altitud":"2576"},{"id":"253074","estado_id":"29","municipio_clave":"8","municipio_id":"2064","clave":"0066","nombre":"La Soledad","latitud":"192147","longitud":"0974129","altitud":"2482"},{"id":"253075","estado_id":"29","municipio_clave":"8","municipio_id":"2064","clave":"0067","nombre":"Rancho Cer\u00f3n","latitud":"192156","longitud":"0974956","altitud":"2482"},{"id":"253076","estado_id":"29","municipio_clave":"8","municipio_id":"2064","clave":"0068","nombre":"El Durazno","latitud":"191926","longitud":"0974415","altitud":"2460"},{"id":"253077","estado_id":"29","municipio_clave":"8","municipio_id":"2064","clave":"0069","nombre":"Factor F\u00e9lix L\u00f3pez","latitud":"191812","longitud":"0974635","altitud":"2460"}]